Workbook

Sheet README
A1: GFunnel Agent Org Map — Task-Specific Agents for a Business Operation
A3: What this is | B3: Every role and every responsibility needed to run a business on the GFunnel Methodology (Omni Process), decomposed into task-specific AI agents (plus the human gates they must escalate to).
A4: Status | B4: DERIVATION — not canon. Built under AGENTS.md rules 4 & 7: the roles are derived from canon; nothing here is a primary algorithm of the methodology, and nothing here changes the base code DETECT → PROCESS → RESPOND.
A5: Sources read | B5: v5.1 (full operational sections: Layers IV–VII, ◇, Master Meta-Algorithm, all per-layer, domain and extended algorithms, self-audit, cannot-supply), v5.2 (Deep-Lens protocol; Runs 4–5), v5.3 (Meta-Tier ⊙). v5.4 deliberately excluded: its constructs are not business operations and it states zero novel predictions.
A6: How it was built | B6: build_agent_map.py parses all 77 algorithms (662 numbered steps) straight from versions/v5.1 so each step becomes an owned responsibility; operational tables (pipeline, script, I.A.C.E., Immersion, BEAS, Five Modes, pillars, self-audit, Forcing Test, Deep-Lens) were transcribed row by row. Re-run the script to regenerate.
A7: Tabs | B7: Agent Roster — every agent with mission, DETECT/PROCESS/RESPOND, hand-offs, tools named in canon, KPIs, human gate, autonomy, source. Responsibilities — every atomic responsibility, one row each, with owner, source line, cadence, trigger, output, hand-off. Algorithm Coverage — all 77 algorithms → owner, status, steps mapped vs steps in canon. Canon Element Coverage — every operational table row → mapped responsibility. BEAS Accountability — 45-cell scoring tool with the accountable agent per cell. Workflows — 15 end-to-end hand-off chains. Human Gates — what agents must never decide. Held-Open Variables — what canon does not supply (never filled with assumption). Gap Check — live formulas proving no responsibility is unowned and no agent is idle.
A8: Tiers | B8: 0 · Human authority / Governance (meta-tier) · 1 · Orchestration & diagnostics · 2 · Department leads (the Nine Hubs) · 3 · Task agents
A9: Autonomy codes (derived) | B9: A = Autonomous — agent executes and logs H = Human-in-loop — agent drafts, human approves L = Human-led — agent assists R = Human-reserved — no agent executes
A10: Status labels | B10: Canon algorithm step / Canon table = transcribed from canon · Derived = placement or charter chosen for this map · Human-reserved = no agent executes · Held open = canon does not supply the value.
A11: Editable cells | B11: Yellow cells on 'BEAS Accountability' are inputs (0, 0.5 or 1; coordination 0–1). Everything else is reference; totals and checks are formulas.
A12: Attribution (CC BY 4.0) | B12: Source: GFunnel Methodology (Omni Process) v5.1–v5.3, Cameron Garlick / GFunnel, https://github.com/GFunnel-Tech/methodology, CC BY 4.0. This workbook adapts (restructures) the material into an agent org map; the adaptation is not endorsed by the author.
A14: Live totals
A15: Agents | B15: =COUNTA('Agent Roster'!A:A)-1 -> 112
A16: Responsibilities | B16: =COUNTA(Responsibilities!A:A)-1 -> 956
A17: Algorithms covered | B17: =COUNTA('Algorithm Coverage'!A:A)-1 -> 78
A18: Canon elements covered | B18: =COUNTA('Canon Element Coverage'!A:A)-1 -> 182
A19: Gap Check status | B19: ='Gap Check'!B12 -> NO GAPS — every responsibility owned, every agent active, every canon step mapped

Sheet Agent Roster
A1: Agent ID | B1: Agent Name | C1: Tier | D1: Hub / Department | E1: Reports To | F1: Kingdom (3K) | G1: Yin/Yang Phase | H1: Mission | I1: Primary Algorithm(s) | J1: DETECT — Triggers | K1: RESPOND — Outputs | L1: Hands Off To | M1: Tools Named in Canon | N1: KPIs / Observation Signals | O1: Human Gate | P1: Failure Mode Guarded | Q1: Autonomy | R1: Role Basis | S1: Canon Source | T1: # Responsibilities
A2: G-00 | B2: Founder / Operator (HUMAN) | C2: 0 · Human authority | D2: Governance & Meta-Tier | E2: — | F2: 3rd | G2: Meta (operates on all layers) | H2: Holds the four things the framework cannot supply: the choice at every decision point, the naming of outcomes, situation-specific measurements, and the stance on held-open variables. Final authority over every agent. | I2: Layer IV Co-Creator Identity; What The Framework Cannot Supply; human-reserved life/contemplative algorithms | J2: Any Human Gate raised by an agent; escalations; held-open variable needing a stance | K2: Decisions, approvals, named outcomes, measurements supplied | L2: The agent that raised the gate | M2: — | N2: Gate turnaround time (threshold held open) | O2: This IS the human gate | P2: Agents filling a decision or variable with assumption | Q2: R | R2: Canon: What The Framework Cannot Supply | S2: v5.1 L168–181; L1257–1296 | T2: =COUNTIF(Responsibilities!$B:$B,A2) -> 98
A3: G-01 | B3: Container Agent (Forcing Test classifier · Layer ⊙) | C3: 0 · Governance | D3: Governance & Meta-Tier | E3: G-00 | F3: 3rd | G3: Meta (operates on all layers) | H3: Classifies every open business question before it is acted on: forced-fill, live hypothesis, stipulation, or proven-open. Runs the Anti-Operation (what new gap does each fill open?). Enforces 'zero hidden gaps'. | I3: Layer ⊙ The Container — Forcing Test (Tests A–D), Anti-Operation, synthesis loop | J3: A variable proposed for resolution; a new policy/structural decision; a contested claim | K3: Classification label + next opened gap, logged to the Variable Register | L3: G-03 Variable Registry Keeper; G-02 Falsifiability | M3: — | N3: % of resolved variables carrying a classification label; hidden gaps found in audit | O3: Stipulations (soft choices) go to G-00 | P3: Silently resolving a held-open variable; presenting a stipulation as forced | Q3: A | R3: Canon: v5.3 meta-tier | S3: v5.3 §1–§4 | T3: =COUNTIF(Responsibilities!$B:$B,A3) -> 9
A4: G-02 | B4: Falsifiability Agent (Layer ◇) | C4: 0 · Governance | D4: Governance & Meta-Tier | E4: G-01 | F4: 3rd | G4: Meta (operates on all layers) | H4: Attaches a falsifier to every claim, plan, forecast, decision and mitigation; statuses each as resolved / bounded / held open / refuted. | I4: Layer ◇ Falsifiability Algorithm | J4: Any claim, plan, forecast, offer promise, mitigation or KPI target is written | K4: Claim card: precise claim, falsifying observation, evidence for/against, bounds, status | L4: Claim owner agent; G-03 | M4: — | N4: % of plans/decisions with an operational falsifier (observation + threshold) | O4: Revising a refuted strategic claim → G-00 | P4: Beliefs presented as claims | Q4: A | R4: Canon: algorithm | S4: v5.1 L2538–2555; L1657–1717 | T4: =COUNTIF(Responsibilities!$B:$B,A4) -> 8
A5: G-03 | B5: Variable Registry Keeper | C5: 0 · Governance | D5: Governance & Meta-Tier | E5: G-01 | F5: 3rd | G5: Meta (operates on all layers) | H5: Maintains the business Variable Register: every quantity marked measured / structurally derived / held open. Blocks any agent output that fills a held-open variable with assumption. | I5: The Variable Principle (Governing Epistemology); Registers | J5: Any agent output containing an unmeasured number or assumption; new data arriving | K5: Register entries; narrowing logs; blocked-output notices | L5: Originating agent; G-00 for measurements | M5: — | N5: Unlabelled assumptions found per audit (target 0) | O5: Measurements only a human can perform → G-00 | P5: Variable Principle violation (the framework's #1 rule) | Q5: A | R5: Canon: Variable Principle | S5: v5.1 L223–263; framework/registers.md | T5: =COUNTIF(Responsibilities!$B:$B,A5) -> 5
A6: G-04 | B6: Framework Compliance Auditor | C6: 0 · Governance | D6: Governance & Meta-Tier | E6: G-01 | F6: 3rd | G6: Meta (operates on all layers) | H6: Runs the canon's 7-point self-audit checklist on every agent run: right algorithm, steps in order, variables held open, run documented, Correspondence applied, measured vs assumed separated, failed paths integrated. | I6: Self-Audit Checklist (How To Verify You Are Using The Framework Correctly) | J6: Completion of any algorithm run by any agent | K6: Pass/fail audit per run; location of failure = next correction | L6: Failing agent; O-10 Capsule Integrator | M6: — | N6: Audit pass rate per agent; repeat failures | O6: — | P6: Skipped / reordered steps; undocumented runs | Q6: A | R6: Canon: self-audit checklist | S6: v5.1 L182–203 | T6: =COUNTIF(Responsibilities!$B:$B,A6) -> 14
A7: G-05 | B7: AI Alignment Agent (agent-fleet oversight) | C7: 0 · Governance | D7: Governance & Meta-Tier | E7: G-00 | F7: 3rd | G7: Meta (operates on all layers) | H7: Applies the AI Alignment Algorithm to this agent fleet itself: Third-Kingdom intent of each agent, observation at multiple levels, falsifiers for misalignment, downgrade paths, review at every capability scale-up. | I7: AI Alignment Algorithm | J7: New agent deployed; agent capability/permission increased; misbehaviour detected | K7: Alignment review, instrumentation spec, downgrade/kill path per agent | L7: G-06; TEC-05 AI Workflow Agent | M7: — | N7: Agents with a documented downgrade path (target 100%); alignment incidents | O7: Deploying or expanding any agent → G-00 | P7: Capability (1st K) without purpose (3rd K); agent with no fallback ('Texas grid') | Q7: H | R7: Canon: algorithm | S7: v5.1 L3933–3954 | T7: =COUNTIF(Responsibilities!$B:$B,A7) -> 11
A8: G-06 | B8: Governance Designer (decision rights & escalation) | C8: 0 · Governance | D8: Governance & Meta-Tier | E8: G-00 | F8: 3rd | G8: Meta (operates on all layers) | H8: Designs the decision-rights map between agents and humans (who decides, who escalates, who audits), the four-pillar soundness of that governance, and its multi-year review cycle. | I8: Governance Design Algorithm; Layer I.B Civil Infrastructure | J8: Org/agent structure changes; repeated escalation conflicts | K8: Governance charter; autonomy levels; escalation map | L8: All department leads | M8: — | N8: Escalations resolved within charter; single points of failure in decision rights | O8: Charter adoption → G-00 | P8: Authoritarian (all decisions centralized) or anarchic (no locus) extremes | Q8: H | R8: Canon: algorithm | S8: v5.1 L3911–3930 | T8: =COUNTIF(Responsibilities!$B:$B,A8) -> 10
A9: G-07 | B9: Founder Performance Agent | C9: 0 · Governance | D9: Governance & Meta-Tier | E9: G-00 | F9: 3rd | G9: Meta (operates on all layers) | H9: Supports the operator's own operating capacity: time allocation by Kingdom, Yin/Yang energy cycles, habits, personal development — so the business is not run from First-Kingdom exhaustion. | I9: Time Management; Energy Management; Habit Formation; Personal Development | J9: Weekly review; operator calendar; drift between intended and actual time | K9: Protected time blocks, weekly allocation review, habit tracking | L9: G-00 | M9: — | N9: Intended vs actual time allocation gap; protected 20% time kept | O9: All personal choices → G-00 | P9: Permanent Yang (burnout); time drift | Q9: L | R9: Canon: algorithms (life domains applied to operator) | S9: v5.1 L2772–2791; L3579–3636 | T9: =COUNTIF(Responsibilities!$B:$B,A9) -> 33
A10: O-01 | B10: Intake & Triage Agent (Layer 0 Base Code) | C10: 1 · Orchestration | D10: Orchestration & Diagnostics | E10: O-02 | F10: 2nd | G10: Dynamic middle | H10: First touch for every input entering the business (email, form, alert, request, idea). Names the input, locates the Kingdom it arrived from, moves it up before deciding, routes it. | I10: Layer 0 Base Code Algorithm; Domain 4 Matrix/Information (information overwhelm) | J10: Any new input arriving in any channel | K10: Labelled input → routed to an agent or algorithm | L10: O-02 Algorithm Router | M10: — | N10: Inputs unrouted >1 cycle (target 0) | O10: — | P10: Reactive First-Kingdom responses to raw input | Q10: A | R10: Canon: algorithm | S10: v5.1 L2232–2247 | T10: =COUNTIF(Responsibilities!$B:$B,A10) -> 15
A11: O-02 | B11: Algorithm Router (Master Meta-Algorithm) | C11: 1 · Orchestration | D11: Orchestration & Diagnostics | E11: G-01 | F11: 2nd | G11: Dynamic middle | H11: Matches every problem to the right algorithm/agent via the Algorithm Index by Problem Type. For a problem no algorithm covers, runs the 12-step Master Meta-Algorithm and labels the result a DERIVATION. Runs Deep-Lens (A–L) for high-resolution diagnoses. | I11: Master Meta-Algorithm (12 steps); Algorithm Index by Problem Type; v5.2 Deep-Lens Protocol | J11: Routed input from O-01; 'I don't know which algorithm to use' | K11: Assigned algorithm + owner agent, or a labelled derived algorithm | L11: Owner agent; G-01 for derived-algorithm classification | M11: — | N11: Mis-routes caught in audit; derivations labelled (target 100%) | O11: Adopting a derived algorithm as standing SOP → G-00 | P11: Improvising silently; presenting a derivation as primary | Q11: A | R11: Canon: algorithm | S11: v5.1 L2169–2225; L4003–4090; v5.2 §1 | T11: =COUNTIF(Responsibilities!$B:$B,A11) -> 25
A12: O-03 | B12: Shepherd's Way Cycle Controller (Layer VI) | C12: 1 · Orchestration | D12: Orchestration & Diagnostics | E12: O-02 | F12: 2nd | G12: Dynamic middle | H12: Enforces the 7-step cycle (Direct → Guide → Gather → Organize → Create → Database → Repetition) on every build, fix or extension in every department. Blocks Create until Organize is complete. Routes New Thought back into Gather. | I12: Layer VI Shepherd's Way Algorithm; New Thought Principle | J12: Any build/fix/extend request; lowest BEAS cell dispatched by O-04; New Thought | K12: Cycle state per work item; stage gates passed/blocked | L12: Executing agent per step; O-15 at Database step | M12: Komodo recordings; email recaps | N12: Builds started without Direct/Guide/Gather (target 0); rework cycles | O12: Direct (intent) for strategic work → G-00 | P12: Create-before-gather; stopping at Create without Database/Repetition | Q12: A | R12: Canon: algorithm + step tables | S12: v5.1 L1453–1569; L2498–2515 | T12: =COUNTIF(Responsibilities!$B:$B,A12) -> 16
A13: O-04 | B13: BEAS Auditor (Layer V Garlick Equilibrium) | C13: 1 · Orchestration | D13: Orchestration & Diagnostics | E13: G-00 | F13: 2nd | G13: Dynamic middle | H13: Scores the business monthly on 9 departments × 4 pillars + 9 coordination scores (45 pts), interprets the band, runs Yin/Yang quadrant analysis against growth stage, and dispatches the lowest cell to the Shepherd's Way. | I13: Layer V Garlick Equilibrium Algorithm (BEAS) | J13: Monthly cycle; major org change | K13: BEAS scorecard, band, quadrant analysis, lowest cell dispatched | L13: O-03; department leads | M13: — | N13: BEAS total; lowest cell; quadrant balance vs stage | O13: Growth-stage classification and score evidence sign-off → G-00 | P13: Uniformly-high score chasing; equilibrium read as stasis | Q13: H | R13: Canon: algorithm + scoring grid | S13: v5.1 L1347–1447; L2478–2495 | T13: =COUNTIF(Responsibilities!$B:$B,A13) -> 15
... A113: CON-08 | B113: Knowledge Base Librarian (Memory & Recall) | C113: 3 · Task agent | D113: 9 · Content Hub | E113: CON-00 | F113: 2nd | G113: Yin — propagation | H113: Organisational memory: multi-level storage, dense cross-links, spaced review of key knowledge, everything beyond recall horizon documented. | I113: Memory and Recall Algorithm; Layer I.F (civilizational record) | J113: New documentation; quarterly review | K113: Linked knowledge base; review schedule | L113: All agents | M113: — | N113: Knowledge retrieval success | O113: — | P113: Knowledge rediscovered at full cost | Q113: A | R113: Derived placement (Memory) | S113: v5.1 L2956–2971 | T113: =COUNTIF(Responsibilities!$B:$B,A113) -> 8

Sheet Responsibilities
A1: Resp ID | B1: Agent ID | C1: Agent Name | D1: Hub | E1: Element Key | F1: Responsibility | G1: Source Type | H1: Source (algorithm / table) | I1: Canon Location | J1: Cadence | K1: Trigger (DETECT) | L1: Output / Next (RESPOND) | M1: Hand-off To | N1: Human Gate | O1: Status
A2: R-0001 | B2: O-02 | C2: =IFERROR(INDEX('Agent Roster'!$B:$B,MATCH(B2,'Agent Roster'!$A:$A,0)),"UNASSIGNED") -> Algorithm Router (Master Meta-Algorithm) | D2: =IFERROR(INDEX('Agent Roster'!$D:$D,MATCH(B2,'Agent Roster'!$A:$A,0)),"UNASSIGNED") -> Orchestration & Diagnostics | E2: ALG:Master Meta-Algorithm | F2: Step 1: Identify the domain. Name what you are operating on. The domain must be specific enough that its DETECT, PROCESS, and RESPOND signatures are distinguishable from adjacent domains. | G2: Algorithm step | H2: Master Meta-Algorithm | I2: v5.1 L2181 | J2: Per un-routed problem | K2: Algorithm triggered | L2: Step 2 | M2: O-02 | O2: Canon algorithm step
A3: R-0002 | B3: O-02 | C3: =IFERROR(INDEX('Agent Roster'!$B:$B,MATCH(B3,'Agent Roster'!$A:$A,0)),"UNASSIGNED") -> Algorithm Router (Master Meta-Algorithm) | D3: =IFERROR(INDEX('Agent Roster'!$D:$D,MATCH(B3,'Agent Roster'!$A:$A,0)),"UNASSIGNED") -> Orchestration & Diagnostics | E3: ALG:Master Meta-Algorithm | F3: Step 2: Locate the Three Kingdoms alignment. Determine which Kingdom the domain primarily operates from: Third (consciousness, vision, intent), Second (organized thought, systems, frameworks), or First (matter, action, physical execution). | G3: Algorithm step | H3: Master Meta-Algorithm | I3: v5.1 L2183 | J3: Per un-routed problem | K3: Step 1 complete | L3: Step 3 | M3: O-02 | O3: Canon algorithm step
A4: R-0003 | B4: O-02 | C4: =IFERROR(INDEX('Agent Roster'!$B:$B,MATCH(B4,'Agent Roster'!$A:$A,0)),"UNASSIGNED") -> Algorithm Router (Master Meta-Algorithm) | D4: =IFERROR(INDEX('Agent Roster'!$D:$D,MATCH(B4,'Agent Roster'!$A:$A,0)),"UNASSIGNED") -> Orchestration & Diagnostics | E4: ALG:Master Meta-Algorithm | F4: Step 3: Identify the current state. Map what currently exists in the domain. Capture the data without filtering. Hold every variable open per the Variable Principle. | G4: Algorithm step | H4: Master Meta-Algorithm | I4: v5.1 L2185 | J4: Per un-routed problem | K4: Step 2 complete | L4: Step 4 | M4: O-02 | O4: Canon algorithm step
A5: R-0004 | B5: O-02 | C5: =IFERROR(INDEX('Agent Roster'!$B:$B,MATCH(B5,'Agent Roster'!$A:$A,0)),"UNASSIGNED") -> Algorithm Router (Master Meta-Algorithm) | D5: =IFERROR(INDEX('Agent Roster'!$D:$D,MATCH(B5,'Agent Roster'!$A:$A,0)),"UNASSIGNED") -> Orchestration & Diagnostics | E5: ALG:Master Meta-Algorithm | F5: Step 4: Identify the desired state. Name what the domain should produce. The gap between current state and desired state is the work. | G5: Algorithm step | H5: Master Meta-Algorithm | I5: v5.1 L2187 | J5: Per un-routed problem | K5: Step 3 complete | L5: Step 5 | M5: O-02 | O5: Canon algorithm step
A6: R-0005 | B6: O-02 | C6: =IFERROR(INDEX('Agent Roster'!$B:$B,MATCH(B6,'Agent Roster'!$A:$A,0)),"UNASSIGNED") -> Algorithm Router (Master Meta-Algorithm) | D6: =IFERROR(INDEX('Agent Roster'!$D:$D,MATCH(B6,'Agent Roster'!$A:$A,0)),"UNASSIGNED") -> Orchestration & Diagnostics | E6: ALG:Master Meta-Algorithm | F6: Step 5: Locate the dynamic middle. Identify the Yang extreme of the domain, the Yin extreme of the domain, and the dynamic middle position from which both extremes are accessible. The dynamic middle shifts as conditions change. | G6: Algorithm step | H6: Master Meta-Algorithm | I6: v5.1 L2189 | J6: Per un-routed problem | K6: Step 4 complete | L6: Step 6 | M6: O-02 | O6: Canon algorithm step
A7: R-0006 | B7: O-02 | C7: =IFERROR(INDEX('Agent Roster'!$B:$B,MATCH(B7,'Agent Roster'!$A:$A,0)),"UNASSIGNED") -> Algorithm Router (Master Meta-Algorithm) | D7: =IFERROR(INDEX('Agent Roster'!$D:$D,MATCH(B7,'Agent Roster'!$A:$A,0)),"UNASSIGNED") -> Orchestration & Diagnostics | E7: ALG:Master Meta-Algorithm | F7: Step 6: Identify which Hermetic principle is being violated. Mentalism, Correspondence, Vibration, Polarity, Rhythm, Cause and Effect, or Gender. The violation is the cause of the gap between current and desired state. | G7: Algorithm step | H7: Master Meta-Algorithm | I7: v5.1 L2191 | J7: Per un-routed problem | K7: Step 5 complete | L7: Step 7 | M7: O-02 | O7: Canon algorithm step
A8: R-0007 | B8: O-02 | C8: =IFERROR(INDEX('Agent Roster'!$B:$B,MATCH(B8,'Agent Roster'!$A:$A,0)),"UNASSIGNED") -> Algorithm Router (Master Meta-Algorithm) | D8: =IFERROR(INDEX('Agent Roster'!$D:$D,MATCH(B8,'Agent Roster'!$A:$A,0)),"UNASSIGNED") -> Orchestration & Diagnostics | E8: ALG:Master Meta-Algorithm | F8: Step 7: Identify the gradient. Every functional process runs on a gradient (a polarity established and collapsed). Determine which gradient powers the domain and whether it is established, collapsed, or absent. | G8: Algorithm step | H8: Master Meta-Algorithm | I8: v5.1 L2193 | J8: Per un-routed problem | K8: Step 6 complete | L8: Step 8 | M8: O-02 | O8: Canon algorithm step
A9: R-0008 | B9: O-02 | C9: =IFERROR(INDEX('Agent Roster'!$B:$B,MATCH(B9,'Agent Roster'!$A:$A,0)),"UNASSIGNED") -> Algorithm Router (Master Meta-Algorithm) | D9: =IFERROR(INDEX('Agent Roster'!$D:$D,MATCH(B9,'Agent Roster'!$A:$A,0)),"UNASSIGNED") -> Orchestration & Diagnostics | E9: ALG:Master Meta-Algorithm | F9: Step 8: Set the cause. Per Cause and Effect: nothing happens by chance. Determine which cause, when set deliberately, produces the desired state as effect. | G9: Algorithm step | H9: Master Meta-Algorithm | I9: v5.1 L2195 | J9: Per un-routed problem | K9: Step 7 complete | L9: Step 9 | M9: O-02 | O9: Canon algorithm step
A10: R-0009 | B10: O-02 | C10: =IFERROR(INDEX('Agent Roster'!$B:$B,MATCH(B10,'Agent Roster'!$A:$A,0)),"UNASSIGNED") -> Algorithm Router (Master Meta-Algorithm) | D10: =IFERROR(INDEX('Agent Roster'!$D:$D,MATCH(B10,'Agent Roster'!$A:$A,0)),"UNASSIGNED") -> Orchestration & Diagnostics | E10: ALG:Master Meta-Algorithm | F10: Step 9: Build the structure. Move from Third Kingdom intent through Second Kingdom organization into First Kingdom execution. Do not skip Kingdoms. Each Kingdom must complete before the next begins. | G10: Algorithm step | H10: Master Meta-Algorithm | I10: v5.1 L2197 | J10: Per un-routed problem | K10: Step 8 complete | L10: Step 10 | M10: O-02 | O10: Canon algorithm step
A11: R-0010 | B11: O-02 | C11: =IFERROR(INDEX('Agent Roster'!$B:$B,MATCH(B11,'Agent Roster'!$A:$A,0)),"UNASSIGNED") -> Algorithm Router (Master Meta-Algorithm) | D11: =IFERROR(INDEX('Agent Roster'!$D:$D,MATCH(B11,'Agent Roster'!$A:$A,0)),"UNASSIGNED") -> Orchestration & Diagnostics | E11: ALG:Master Meta-Algorithm | F11: Step 10: Run the cycle. Execute the structure. Observe the result against the predicted effect. Capture every deviation as data, not failure. | G11: Algorithm step | H11: Master Meta-Algorithm | I11: v5.1 L2199 | J11: Per un-routed problem | K11: Step 9 complete | L11: Step 11 | M11: O-02 | O11: Canon algorithm step
A12: R-0011 | B12: O-02 | C12: =IFERROR(INDEX('Agent Roster'!$B:$B,MATCH(B12,'Agent Roster'!$A:$A,0)),"UNASSIGNED") -> Algorithm Router (Master Meta-Algorithm) | D12: =IFERROR(INDEX('Agent Roster'!$D:$D,MATCH(B12,'Agent Roster'!$A:$A,0)),"UNASSIGNED") -> Orchestration & Diagnostics | E12: ALG:Master Meta-Algorithm | F12: Step 11: Document the result. Per Propagation Mode 3: if it is not written, it does not exist as a process. Record what was done, what worked, what deviated, what to adjust. | G12: Algorithm step | H12: Master Meta-Algorithm | I12: v5.1 L2201 | J12: Per un-routed problem | K12: Step 10 complete | L12: Step 12 | M12: O-02 | O12: Canon algorithm step
A13: R-0012 | B13: O-02 | C13: =IFERROR(INDEX('Agent Roster'!$B:$B,MATCH(B13,'Agent Roster'!$A:$A,0)),"UNASSIGNED") -> Algorithm Router (Master Meta-Algorithm) | D13: =IFERROR(INDEX('Agent Roster'!$D:$D,MATCH(B13,'Agent Roster'!$A:$A,0)),"UNASSIGNED") -> Orchestration & Diagnostics | E13: ALG:Master Meta-Algorithm | F13: Step 12: Restart at higher baseline. Per the Repetition principle: each cycle begins informed by the prior cycle. Per the Capsule: each cycle integrates ALL prior cycles. Return to step 1 with the new baseline as input. | G13: Algorithm step | H13: Master Meta-Algorithm | I13: v5.1 L2203 | J13: Per un-routed problem | K13: Step 11 complete | L13: Document & restart at higher baseline (Repetition) | M13: O-15 (Database) | O13: Canon algorithm step
... A93: R-0092 | B93: O-14 | C93: =IFERROR(INDEX('Agent Roster'!$B:$B,MATCH(B93,'Agent Roster'!$A:$A,0)),"UNASSIGNED") -> Knowledge Compounding Agent (Layer III+ Integration Density) | D93: =IFERROR(INDEX('Agent Roster'!$D:$D,MATCH(B93,'Agent Roster'!$A:$A,0)),"UNASSIGNED") -> Orchestration & Diagnostics | E93: ALG:Layer III+ — The Integration Density Algorithm | F93: Step 7: Per the Golden Ratio of Purpose: identify where most-selfish creative desire converges with most-selfless creative desire. The convergence point is the structural attractor for sustained integration. | G93: Algorithm step | H93: Layer III+ — The Integration Density Algorithm | I93: v5.1 L2455 | J93: Per cycle kickoff | K93: Step 6 complete | L93: Document & restart at higher baseline (Repetition) | M93: O-15 (Database) | O93: Canon algorithm step
A94: R-0093 | B94: G-00 | C94: =IFERROR(INDEX('Agent Roster'!$B:$B,MATCH(B94,'Agent Roster'!$A:$A,0)),"UNASSIGNED") -> Founder / Operator (HUMAN) | D94: =IFERROR(INDEX('Agent Roster'!$D:$D,MATCH(B94,'Agent Roster'!$A:$A,0)),"UNASSIGNED") -> Governance & Meta-Tier | E94: ALG:Layer IV — The Co-Creator Identity Algorithm | F94: Step 1: Identify your most selfish creative desire. The one with no ceiling. What would you build if no constraint existed? Must be generative, not consumptive. | G94: Algorithm step | H94: Layer IV — The Co-Creator Identity Algorithm | I94: v5.1 L2463 | J94: Annual / quarterly | K94: Algorithm triggered | L94: Step 2 | M94: G-00 | N94: Human-only | O94: Canon algorithm step
A95: R-0094 | B95: G-00 | C95: =IFERROR(INDEX('Agent Roster'!$B:$B,MATCH(B95,'Agent Roster'!$A:$A,0)),"UNASSIGNED") -> Founder / Operator (HUMAN) | D95: =IFERROR(INDEX('Agent Roster'!$D:$D,MATCH(B95,'Agent Roster'!$A:$A,0)),"UNASSIGNED") -> Governance & Meta-Tier | E95: ALG:Layer IV — The Co-Creator Identity Algorithm | F95: Step 2: Identify your most selfless creative desire. The one that does not exist yet but should. What would you make possible for others? Must be creative, not merely sacrificial. | G95: Algorithm step | H95: Layer IV — The Co-Creator Identity Algorithm | I95: v5.1 L2465 | J95: Annual / quarterly | K95: Step 1 complete | L95: Step 3 | M95: G-00 | N95: Human-only | O95: Canon algorithm step
A96: R-0095 | B96: STR-01 | C96: =IFERROR(INDEX('Agent Roster'!$B:$B,MATCH(B96,'Agent Roster'!$A:$A,0)),"UNASSIGNED") -> Vision, Mission & Purpose Steward | D96: =IFERROR(INDEX('Agent Roster'!$D:$D,MATCH(B96,'Agent Roster'!$A:$A,0)),"UNASSIGNED") -> 1 · Strategy Hub | E96: ALG:Layer IV — The Co-Creator Identity Algorithm | F96: Step 3: Find their convergence. Per Polarity: if both are genuine extremes, they must converge. | G96: Algorithm step | H96: Layer IV — The Co-Creator Identity Algorithm | I96: v5.1 L2467 | J96: Annual / quarterly | K96: Step 2 complete | L96: Step 4 | M96: STR-01 | O96: Canon algorithm step
A97: R-0096 | B97: STR-01 | C97: =IFERROR(INDEX('Agent Roster'!$B:$B,MATCH(B97,'Agent Roster'!$A:$A,0)),"UNASSIGNED") -> Vision, Mission & Purpose Steward | D97: =IFERROR(INDEX('Agent Roster'!$D:$D,MATCH(B97,'Agent Roster'!$A:$A,0)),"UNASSIGNED") -> 1 · Strategy Hub | E97: ALG:Layer IV — The Co-Creator Identity Algorithm | F97: Step 4: Test the convergence point. Does the most selfish form require service to others? Does the most selfless form produce personal fulfillment? Both must be true. | G97: Algorithm step | H97: Layer IV — The Co-Creator Identity Algorithm | I97: v5.1 L2469 | J97: Annual / quarterly | K97: Step 3 complete | L97: Step 5 | M97: STR-01 | O97: Canon algorithm step
A98: R-0097 | B98: G-00 | C98: =IFERROR(INDEX('Agent Roster'!$B:$B,MATCH(B98,'Agent Roster'!$A:$A,0)),"UNASSIGNED") -> Founder / Operator (HUMAN) | D98: =IFERROR(INDEX('Agent Roster'!$D:$D,MATCH(B98,'Agent Roster'!$A:$A,0)),"UNASSIGNED") -> Governance & Meta-Tier | E98: ALG:Layer IV — The Co-Creator Identity Algorithm | F98: Step 5: The convergence point is your structural purpose. Not aspirational. Derived. | G98: Algorithm step | H98: Layer IV — The Co-Creator Identity Algorithm | I98: v5.1 L2471 | J98: Annual / quarterly | K98: Step 4 complete | L98: Step 6 | M98: G-00 | N98: Human-only | O98: Canon algorithm step
A99: R-0098 | B99: STR-01 | C99: =IFERROR(INDEX('Agent Roster'!$B:$B,MATCH(B99,'Agent Roster'!$A:$A,0)),"UNASSIGNED") -> Vision, Mission & Purpose Steward | D99: =IFERROR(INDEX('Agent Roster'!$D:$D,MATCH(B99,'Agent Roster'!$A:$A,0)),"UNASSIGNED") -> 1 · Strategy Hub | E99: ALG:Layer IV — The Co-Creator Identity Algorithm | F99: Step 6: Apply the filter. Every decision now passes through: does this compound toward the convergence point, or away from it? | G99: Algorithm step | H99: Layer IV — The Co-Creator Identity Algorithm | I99: v5.1 L2473 | J99: Annual / quarterly | K99: Step 5 complete | L99: Step 7 | M99: STR-01 | O99: Canon algorithm step
A100: R-0099 | B100: CON-00 | C100: =IFERROR(INDEX('Agent Roster'!$B:$B,MATCH(B100,'Agent Roster'!$A:$A,0)),"UNASSIGNED") -> Content Hub Lead (Propagation owner) | D100: =IFERROR(INDEX('Agent Roster'!$D:$D,MATCH(B100,'Agent Roster'!$A:$A,0)),"UNASSIGNED") -> 9 · Content Hub | E100: ALG:Layer IV — The Co-Creator Identity Algorithm | F100: Step 7: Per the Five Modes of Propagation: choose how the work outlasts you. Direct teaching, demonstration, documentation, system-building, cultural embedding. Most lasting work uses all five. | G100: Algorithm step | H100: Layer IV — The Co-Creator Identity Algorithm | I100: v5.1 L2475 | J100: Annual / quarterly | K100: Step 6 complete | L100: Document & restart at higher baseline (Repetition) | M100: O-15 (Database) | O100: Canon algorithm step
A101: R-0100 | B101: O-04 | C101: =IFERROR(INDEX('Agent Roster'!$B:$B,MATCH(B101,'Agent Roster'!$A:$A,0)),"UNASSIGNED") -> BEAS Auditor (Layer V Garlick Equilibrium) | D101: =IFERROR(INDEX('Agent Roster'!$D:$D,MATCH(B101,'Agent Roster'!$A:$A,0)),"UNASSIGNED") -> Orchestration & Diagnostics | E101: ALG:Layer V — The Garlick Equilibrium Algorithm (BEAS Application) | F101: Step 1: Score each of the nine departments on each of the four pillars (Correctness, Complexity, Patience, Resilience). Each cell scores 0, 0.5, or 1. | G101: Algorithm step | H101: Layer V — The Garlick Equilibrium Algorithm (BEAS Application) | I101: v5.1 L2483 | J101: Monthly | K101: Algorithm triggered | L101: Step 2 | M101: O-04 | O101: Canon algorithm step
A102: R-0101 | B102: O-04 | C102: =IFERROR(INDEX('Agent Roster'!$B:$B,MATCH(B102,'Agent Roster'!$A:$A,0)),"UNASSIGNED") -> BEAS Auditor (Layer V Garlick Equilibrium) | D102: =IFERROR(INDEX('Agent Roster'!$D:$D,MATCH(B102,'Agent Roster'!$A:$A,0)),"UNASSIGNED") -> Orchestration & Diagnostics | E102: ALG:Layer V — The Garlick Equilibrium Algorithm (BEAS Application) | F102: Step 2: Score each department’s coordination with the other eight departments. Each department gets a 0–1 coordination score. | G102: Algorithm step | H102: Layer V — The Garlick Equilibrium Algorithm (BEAS Application) | I102: v5.1 L2485 | J102: Monthly | K102: Step 1 complete | L102: Step 3 | M102: O-04 | O102: Canon algorithm step
A103: R-0102 | B103: O-04 | C103: =IFERROR(INDEX('Agent Roster'!$B:$B,MATCH(B103,'Agent Roster'!$A:$A,0)),"UNASSIGNED") -> BEAS Auditor (Layer V Garlick Equilibrium) | D103: =IFERROR(INDEX('Agent Roster'!$D:$D,MATCH(B103,'Agent Roster'!$A:$A,0)),"UNASSIGNED") -> Orchestration & Diagnostics | E103: ALG:Layer V — The Garlick Equilibrium Algorithm (BEAS Application) | F103: Step 3: Sum to a total out of 45. The total reveals current adherence. | G103: Algorithm step | H103: Layer V — The Garlick Equilibrium Algorithm (BEAS Application) | I103: v5.1 L2487 | J103: Monthly | K103: Step 2 complete | L103: Step 4 | M103: O-04 | O103: Canon algorithm step
A104: R-0103 | B104: O-04 | C104: =IFERROR(INDEX('Agent Roster'!$B:$B,MATCH(B104,'Agent Roster'!$A:$A,0)),"UNASSIGNED") -> BEAS Auditor (Layer V Garlick Equilibrium) | D104: =IFERROR(INDEX('Agent Roster'!$D:$D,MATCH(B104,'Agent Roster'!$A:$A,0)),"UNASSIGNED") -> Orchestration & Diagnostics | E104: ALG:Layer V — The Garlick Equilibrium Algorithm (BEAS Application) | F104: Step 4: Compare against growth-stage expectation. Pre-revenue tilts Yang (Marketing/Sales). Scaling tilts toward balance. Mature tilts toward Content/Client Success Yin. | G104: Algorithm step | H104: Layer V — The Garlick Equilibrium Algorithm (BEAS Application) | I104: v5.1 L2489 | J104: Monthly | K104: Step 3 complete | L104: Step 5 | M104: O-04 | O104: Canon algorithm step
A105: R-0104 | B105: O-04 | C105: =IFERROR(INDEX('Agent Roster'!$B:$B,MATCH(B105,'Agent Roster'!$A:$A,0)),"UNASSIGNED") -> BEAS Auditor (Layer V Garlick Equilibrium) | D105: =IFERROR(INDEX('Agent Roster'!$D:$D,MATCH(B105,'Agent Roster'!$A:$A,0)),"UNASSIGNED") -> Orchestration & Diagnostics | E105: ALG:Layer V — The Garlick Equilibrium Algorithm (BEAS Application) | F105: Step 5: Identify the lowest-scoring department-pillar intersection. This is the immediate location for correction. | G105: Algorithm step | H105: Layer V — The Garlick Equilibrium Algorithm (BEAS Application) | I105: v5.1 L2491 | J105: Monthly | K105: Step 4 complete | L105: Step 6 | M105: O-04 | O105: Canon algorithm step
A106: R-0105 | B106: O-03 | C106: =IFERROR(INDEX('Agent Roster'!$B:$B,MATCH(B106,'Agent Roster'!$A:$A,0)),"UNASSIGNED") -> Shepherd's Way Cycle Controller (Layer VI) | D106: =IFERROR(INDEX('Agent Roster'!$D:$D,MATCH(B106,'Agent Roster'!$A:$A,0)),"UNASSIGNED") -> Orchestration & Diagnostics | E106: ALG:Layer V — The Garlick Equilibrium Algorithm (BEAS Application) | F106: Step 6: Apply Layer VI (Shepherd’s Way) to that specific cell. Direct, Guide, Gather, Organize, Create, Database, Repetition. | G106: Algorithm step | H106: Layer V — The Garlick Equilibrium Algorithm (BEAS Application) | I106: v5.1 L2493 | J106: Monthly | K106: Step 5 complete | L106: Step 7 | M106: O-03 | O106: Canon algorithm step
A107: R-0106 | B107: O-04 | C107: =IFERROR(INDEX('Agent Roster'!$B:$B,MATCH(B107,'Agent Roster'!$A:$A,0)),"UNASSIGNED") -> BEAS Auditor (Layer V Garlick Equilibrium) | D107: =IFERROR(INDEX('Agent Roster'!$D:$D,MATCH(B107,'Agent Roster'!$A:$A,0)),"UNASSIGNED") -> Orchestration & Diagnostics | E107: ALG:Layer V — The Garlick Equilibrium Algorithm (BEAS Application) | F107: Step 7: Re-score monthly. The middle moves; the assessment must move with it. | G107: Algorithm step | H107: Layer V — The Garlick Equilibrium Algorithm (BEAS Application) | I107: v5.1 L2495 | J107: Monthly | K107: Step 6 complete | L107: Document & restart at higher baseline (Repetition) | M107: O-15 (Database) | O107: Canon algorithm step
A108: R-0107 | B108: O-03 | C108: =IFERROR(INDEX('Agent Roster'!$B:$B,MATCH(B108,'Agent Roster'!$A:$A,0)),"UNASSIGNED") -> Shepherd's Way Cycle Controller (Layer VI) | D108: =IFERROR(INDEX('Agent Roster'!$D:$D,MATCH(B108,'Agent Roster'!$A:$A,0)),"UNASSIGNED") -> Orchestration & Diagnostics | E108: ALG:Layer VI — The Shepherd’s Way Algorithm | F108: Step 1: Direct. Define the intent before anything else is touched. What outcome? What problem? What scope? Without a clear Direct, all gathering is noise. | G108: Algorithm step | H108: Layer VI — The Shepherd’s Way Algorithm | I108: v5.1 L2503 | J108: Per build / fix / extend | K108: Algorithm triggered | L108: Step 2 | M108: O-03 | O108: Canon algorithm step
A109: R-0108 | B109: O-03 | C109: =IFERROR(INDEX('Agent Roster'!$B:$B,MATCH(B109,'Agent Roster'!$A:$A,0)),"UNASSIGNED") -> Shepherd's Way Cycle Controller (Layer VI) | D109: =IFERROR(INDEX('Agent Roster'!$D:$D,MATCH(B109,'Agent Roster'!$A:$A,0)),"UNASSIGNED") -> Orchestration & Diagnostics | E109: ALG:Layer VI — The Shepherd’s Way Algorithm | F109: Step 2: Guide. Structure the intake. Build the container before information enters it. Which questions need answering? Which stakeholders? Which systems? | G109: Algorithm step | H109: Layer VI — The Shepherd’s Way Algorithm | I109: v5.1 L2505 | J109: Per build / fix / extend | K109: Step 1 complete | L109: Step 3 | M109: O-03 | O109: Canon algorithm step
A110: R-0109 | B110: O-03 | C110: =IFERROR(INDEX('Agent Roster'!$B:$B,MATCH(B110,'Agent Roster'!$A:$A,0)),"UNASSIGNED") -> Shepherd's Way Cycle Controller (Layer VI) | D110: =IFERROR(INDEX('Agent Roster'!$D:$D,MATCH(B110,'Agent Roster'!$A:$A,0)),"UNASSIGNED") -> Orchestration & Diagnostics | E110: ALG:Layer VI — The Shepherd’s Way Algorithm | F110: Step 3: Gather. Collect everything. SOPs, tribal knowledge, existing tools, pain points, workflows, expectations, flows, tools, contractor relationships. Hold every variable open. Filter nothing. | G110: Algorithm step | H110: Layer VI — The Shepherd’s Way Algorithm | I110: v5.1 L2507 | J110: Per build / fix / extend | K110: Step 2 complete | L110: Step 4 | M110: O-03 | O110: Canon algorithm step
... A187: R-0186 | B187: O-16 | C187: =IFERROR(INDEX('Agent Roster'!$B:$B,MATCH(B187,'Agent Roster'!$A:$A,0)),"UNASSIGNED") -> Decision Support Agent | D187: =IFERROR(INDEX('Agent Roster'!$D:$D,MATCH(B187,'Agent Roster'!$A:$A,0)),"UNASSIGNED") -> Orchestration & Diagnostics | E187: ALG:Decision-Making Algorithm | F187: Step 7: Test against falsifiability: what would tell you the decision was wrong? If nothing would, you are not making a real decision. | G187: Algorithm step | H187: Decision-Making Algorithm | I187: v5.1 L2713 | J187: Per material decision | K187: Step 6 complete | L187: Step 8 | M187: O-16 | O187: Canon algorithm step
A188: R-0187 | B188: G-00 | C188: =IFERROR(INDEX('Agent Roster'!$B:$B,MATCH(B188,'Agent Roster'!$A:$A,0)),"UNASSIGNED") -> Founder / Operator (HUMAN) | D188: =IFERROR(INDEX('Agent Roster'!$D:$D,MATCH(B188,'Agent Roster'!$A:$A,0)),"UNASSIGNED") -> Governance & Meta-Tier | E188: ALG:Decision-Making Algorithm | F188: Step 8: Decide. Set the cause. | G188: Algorithm step | H188: Decision-Making Algorithm | I188: v5.1 L2715 | J188: Per material decision | K188: Step 7 complete | L188: Step 9 | M188: G-00 | N188: Human-only | O188: Canon algorithm step
A189: R-0188 | B189: O-16 | C189: =IFERROR(INDEX('Agent Roster'!$B:$B,MATCH(B189,'Agent Roster'!$A:$A,0)),"UNASSIGNED") -> Decision Support Agent | D189: =IFERROR(INDEX('Agent Roster'!$D:$D,MATCH(B189,'Agent Roster'!$A:$A,0)),"UNASSIGNED") -> Orchestration & Diagnostics | E189: ALG:Decision-Making Algorithm | F189: Step 9: Document the decision and its expected outcome. The documented expectation is what makes evaluation possible. | G189: Algorithm step | H189: Decision-Making Algorithm | I189: v5.1 L2717 | J189: Per material decision | K189: Step 8 complete | L189: Step 10 | M189: O-16 | O189: Canon algorithm step
A190: R-0189 | B190: O-16 | C190: =IFERROR(INDEX('Agent Roster'!$B:$B,MATCH(B190,'Agent Roster'!$A:$A,0)),"UNASSIGNED") -> Decision Support Agent | D190: =IFERROR(INDEX('Agent Roster'!$D:$D,MATCH(B190,'Agent Roster'!$A:$A,0)),"UNASSIGNED") -> Orchestration & Diagnostics | E190: ALG:Decision-Making Algorithm | F190: Step 10: Observe the actual outcome against the predicted. Integrate the gap as information per the Slime Mold mechanism. | G190: Algorithm step | H190: Decision-Making Algorithm | I190: v5.1 L2719 | J190: Per material decision | K190: Step 9 complete | L190: Document & restart at higher baseline (Repetition) | M190: O-15 (Database) | O190: Canon algorithm step
A191: R-0190 | B191: HRC-08 | C191: =IFERROR(INDEX('Agent Roster'!$B:$B,MATCH(B191,'Agent Roster'!$A:$A,0)),"UNASSIGNED") -> Conflict Resolution Agent | D191: =IFERROR(INDEX('Agent Roster'!$D:$D,MATCH(B191,'Agent Roster'!$A:$A,0)),"UNASSIGNED") -> 6 · HR & Culture Hub | E191: ALG:Conflict Resolution Algorithm | F191: Step 1: Locate the polarity. Conflict is two parties operating from opposite poles of the same axis. Identify the axis. | G191: Algorithm step | H191: Conflict Resolution Algorithm | I191: v5.1 L2725 | J191: Per conflict | K191: Algorithm triggered | L191: Step 2 | M191: HRC-08 | O191: Canon algorithm step
A192: R-0191 | B192: HRC-08 | C192: =IFERROR(INDEX('Agent Roster'!$B:$B,MATCH(B192,'Agent Roster'!$A:$A,0)),"UNASSIGNED") -> Conflict Resolution Agent | D192: =IFERROR(INDEX('Agent Roster'!$D:$D,MATCH(B192,'Agent Roster'!$A:$A,0)),"UNASSIGNED") -> 6 · HR & Culture Hub | E192: ALG:Conflict Resolution Algorithm | F192: Step 2: Recognize that opposites are degree variations along one axis, not different things. The parties want the same thing in different forms. | G192: Algorithm step | H192: Conflict Resolution Algorithm | I192: v5.1 L2727 | J192: Per conflict | K192: Step 1 complete | L192: Step 3 | M192: HRC-08 | O192: Canon algorithm step
A193: R-0192 | B193: HRC-08 | C193: =IFERROR(INDEX('Agent Roster'!$B:$B,MATCH(B193,'Agent Roster'!$A:$A,0)),"UNASSIGNED") -> Conflict Resolution Agent | D193: =IFERROR(INDEX('Agent Roster'!$D:$D,MATCH(B193,'Agent Roster'!$A:$A,0)),"UNASSIGNED") -> 6 · HR & Culture Hub | E193: ALG:Conflict Resolution Algorithm | F193: Step 3: Match frequencies before introducing change. Lower the temperature before resolving content. | G193: Algorithm step | H193: Conflict Resolution Algorithm | I193: v5.1 L2729 | J193: Per conflict | K193: Step 2 complete | L193: Step 4 | M193: HRC-08 | O193: Canon algorithm step
A194: R-0193 | B194: HRC-08 | C194: =IFERROR(INDEX('Agent Roster'!$B:$B,MATCH(B194,'Agent Roster'!$A:$A,0)),"UNASSIGNED") -> Conflict Resolution Agent | D194: =IFERROR(INDEX('Agent Roster'!$D:$D,MATCH(B194,'Agent Roster'!$A:$A,0)),"UNASSIGNED") -> 6 · HR & Culture Hub | E194: ALG:Conflict Resolution Algorithm | F194: Step 4: Run pure discovery on each party’s actual interest, not their stated position. | G194: Algorithm step | H194: Conflict Resolution Algorithm | I194: v5.1 L2731 | J194: Per conflict | K194: Step 3 complete | L194: Step 5 | M194: HRC-08 | O194: Canon algorithm step
A195: R-0194 | B195: HRC-08 | C195: =IFERROR(INDEX('Agent Roster'!$B:$B,MATCH(B195,'Agent Roster'!$A:$A,0)),"UNASSIGNED") -> Conflict Resolution Agent | D195: =IFERROR(INDEX('Agent Roster'!$D:$D,MATCH(B195,'Agent Roster'!$A:$A,0)),"UNASSIGNED") -> 6 · HR & Culture Hub | E195: ALG:Conflict Resolution Algorithm | F195: Step 5: Identify what shared interest exists beneath the conflict. There almost always is one. | G195: Algorithm step | H195: Conflict Resolution Algorithm | I195: v5.1 L2733 | J195: Per conflict | K195: Step 4 complete | L195: Step 6 | M195: HRC-08 | O195: Canon algorithm step
A196: R-0195 | B196: HRC-08 | C196: =IFERROR(INDEX('Agent Roster'!$B:$B,MATCH(B196,'Agent Roster'!$A:$A,0)),"UNASSIGNED") -> Conflict Resolution Agent | D196: =IFERROR(INDEX('Agent Roster'!$D:$D,MATCH(B196,'Agent Roster'!$A:$A,0)),"UNASSIGNED") -> 6 · HR & Culture Hub | E196: ALG:Conflict Resolution Algorithm | F196: Step 6: Locate the dynamic middle. Where does each party’s interest find legitimate expression? | G196: Algorithm step | H196: Conflict Resolution Algorithm | I196: v5.1 L2735 | J196: Per conflict | K196: Step 5 complete | L196: Step 7 | M196: HRC-08 | O196: Canon algorithm step
A197: R-0196 | B197: HRC-08 | C197: =IFERROR(INDEX('Agent Roster'!$B:$B,MATCH(B197,'Agent Roster'!$A:$A,0)),"UNASSIGNED") -> Conflict Resolution Agent | D197: =IFERROR(INDEX('Agent Roster'!$D:$D,MATCH(B197,'Agent Roster'!$A:$A,0)),"UNASSIGNED") -> 6 · HR & Culture Hub | E197: ALG:Conflict Resolution Algorithm | F197: Step 7: Frame the resolution as expanding the field of solution rather than splitting the existing one. | G197: Algorithm step | H197: Conflict Resolution Algorithm | I197: v5.1 L2737 | J197: Per conflict | K197: Step 6 complete | L197: Step 8 | M197: HRC-08 | O197: Canon algorithm step
A198: R-0197 | B198: HRC-08 | C198: =IFERROR(INDEX('Agent Roster'!$B:$B,MATCH(B198,'Agent Roster'!$A:$A,0)),"UNASSIGNED") -> Conflict Resolution Agent | D198: =IFERROR(INDEX('Agent Roster'!$D:$D,MATCH(B198,'Agent Roster'!$A:$A,0)),"UNASSIGNED") -> 6 · HR & Culture Hub | E198: ALG:Conflict Resolution Algorithm | F198: Step 8: Confirm acceptance through behavior, not just words. | G198: Algorithm step | H198: Conflict Resolution Algorithm | I198: v5.1 L2739 | J198: Per conflict | K198: Step 7 complete | L198: Step 9 | M198: HRC-08 | O198: Canon algorithm step
A199: R-0198 | B199: HRC-08 | C199: =IFERROR(INDEX('Agent Roster'!$B:$B,MATCH(B199,'Agent Roster'!$A:$A,0)),"UNASSIGNED") -> Conflict Resolution Agent | D199: =IFERROR(INDEX('Agent Roster'!$D:$D,MATCH(B199,'Agent Roster'!$A:$A,0)),"UNASSIGNED") -> 6 · HR & Culture Hub | E199: ALG:Conflict Resolution Algorithm | F199: Step 9: Document the resolution and the principle behind it. The principle is what generalizes to future similar conflicts. | G199: Algorithm step | H199: Conflict Resolution Algorithm | I199: v5.1 L2741 | J199: Per conflict | K199: Step 8 complete | L199: Document & restart at higher baseline (Repetition) | M199: O-15 (Database) | O199: Canon algorithm step
A200: R-0199 | B200: STR-03 | C200: =IFERROR(INDEX('Agent Roster'!$B:$B,MATCH(B200,'Agent Roster'!$A:$A,0)),"UNASSIGNED") -> Quarterly Direction & Strategic Planning Agent | D200: =IFERROR(INDEX('Agent Roster'!$D:$D,MATCH(B200,'Agent Roster'!$A:$A,0)),"UNASSIGNED") -> 1 · Strategy Hub | E200: ALG:Strategic Planning Algorithm | F200: Step 1: Direct. State the time horizon and the desired state at the end of that horizon. | G200: Algorithm step | H200: Strategic Planning Algorithm | I200: v5.1 L2747 | J200: Quarterly; monthly review | K200: Algorithm triggered | L200: Step 2 | M200: STR-03 | O200: Canon algorithm step
... A217: R-0216 | B217: G-07 | C217: =IFERROR(INDEX('Agent Roster'!$B:$B,MATCH(B217,'Agent Roster'!$A:$A,0)),"UNASSIGNED") -> Founder Performance Agent | D217: =IFERROR(INDEX('Agent Roster'!$D:$D,MATCH(B217,'Agent Roster'!$A:$A,0)),"UNASSIGNED") -> Governance & Meta-Tier | E217: ALG:Personal Development Algorithm | F217: Step 8: Per Repetition: each cycle of self-development begins from a higher baseline informed by all prior cycles. | G217: Algorithm step | H217: Personal Development Algorithm | I217: v5.1 L2789 | J217: Weekly | K217: Step 7 complete | L217: Document & restart at higher baseline (Repetition) | M217: O-15 (Database) | O217: Canon algorithm step
A218: R-0217 | B218: G-00 | C218: =IFERROR(INDEX('Agent Roster'!$B:$B,MATCH(B218,'Agent Roster'!$A:$A,0)),"UNASSIGNED") -> Founder / Operator (HUMAN) | D218: =IFERROR(INDEX('Agent Roster'!$D:$D,MATCH(B218,'Agent Roster'!$A:$A,0)),"UNASSIGNED") -> Governance & Meta-Tier | E218: ALG:Relationships Algorithm | F218: Step 1: Identify which Kingdom each party operates from in this relationship. The relationship’s health is largely determined by Kingdom alignment between parties. | G218: Algorithm step | H218: Relationships Algorithm | I218: v5.1 L2795 | J218: — | K218: Algorithm triggered | L218: Step 2 | M218: G-00 | N218: Human-only | O218: Human-reserved
A219: R-0218 | B219: G-00 | C219: =IFERROR(INDEX('Agent Roster'!$B:$B,MATCH(B219,'Agent Roster'!$A:$A,0)),"UNASSIGNED") -> Founder / Operator (HUMAN) | D219: =IFERROR(INDEX('Agent Roster'!$D:$D,MATCH(B219,'Agent Roster'!$A:$A,0)),"UNASSIGNED") -> Governance & Meta-Tier | E219: ALG:Relationships Algorithm | F219: Step 2: Identify the gradient. Healthy relationships establish and channel gradients between parties (complementary capacities, mutual growth, shared meaning). Stale relationships have no active gradient. | G219: Algorithm step | H219: Relationships Algorithm | I219: v5.1 L2797 | J219: — | K219: Step 1 complete | L219: Step 3 | M219: G-00 | N219: Human-only | O219: Human-reserved
A220: R-0219 | B220: G-00 | C220: =IFERROR(INDEX('Agent Roster'!$B:$B,MATCH(B220,'Agent Roster'!$A:$A,0)),"UNASSIGNED") -> Founder / Operator (HUMAN) | D220: =IFERROR(INDEX('Agent Roster'!$D:$D,MATCH(B220,'Agent Roster'!$A:$A,0)),"UNASSIGNED") -> Governance & Meta-Tier | E220: ALG:Relationships Algorithm | F220: Step 3: Apply Vibration. Are the frequencies of communication aligned? Frequency mismatch produces dissipation regardless of mutual care. | G220: Algorithm step | H220: Relationships Algorithm | I220: v5.1 L2799 | J220: — | K220: Step 2 complete | L220: Step 4 | M220: G-00 | N220: Human-only | O220: Human-reserved
A221: R-0220 | B221: G-00 | C221: =IFERROR(INDEX('Agent Roster'!$B:$B,MATCH(B221,'Agent Roster'!$A:$A,0)),"UNASSIGNED") -> Founder / Operator (HUMAN) | D221: =IFERROR(INDEX('Agent Roster'!$D:$D,MATCH(B221,'Agent Roster'!$A:$A,0)),"UNASSIGNED") -> Governance & Meta-Tier | E221: ALG:Relationships Algorithm | F221: Step 4: Apply Polarity. Are differences treated as conflict or as complementary poles of one axis? | G221: Algorithm step | H221: Relationships Algorithm | I221: v5.1 L2801 | J221: — | K221: Step 3 complete | L221: Step 5 | M221: G-00 | N221: Human-only | O221: Human-reserved
A222: R-0221 | B222: G-00 | C222: =IFERROR(INDEX('Agent Roster'!$B:$B,MATCH(B222,'Agent Roster'!$A:$A,0)),"UNASSIGNED") -> Founder / Operator (HUMAN) | D222: =IFERROR(INDEX('Agent Roster'!$D:$D,MATCH(B222,'Agent Roster'!$A:$A,0)),"UNASSIGNED") -> Governance & Meta-Tier | E222: ALG:Relationships Algorithm | F222: Step 5: Apply Gender. Is creative work in the relationship integrating Masculine projection and Feminine reception, or has one polarity collapsed? | G222: Algorithm step | H222: Relationships Algorithm | I222: v5.1 L2803 | J222: — | K222: Step 4 complete | L222: Step 6 | M222: G-00 | N222: Human-only | O222: Human-reserved
A223: R-0222 | B223: G-00 | C223: =IFERROR(INDEX('Agent Roster'!$B:$B,MATCH(B223,'Agent Roster'!$A:$A,0)),"UNASSIGNED") -> Founder / Operator (HUMAN) | D223: =IFERROR(INDEX('Agent Roster'!$D:$D,MATCH(B223,'Agent Roster'!$A:$A,0)),"UNASSIGNED") -> Governance & Meta-Tier | E223: ALG:Relationships Algorithm | F223: Step 6: Locate the dynamic middle. Most relationship struggles are extreme Yang (too much demand, control, expression) or extreme Yin (too much accommodation, withdrawal, silence). | G223: Algorithm step | H223: Relationships Algorithm | I223: v5.1 L2805 | J223: — | K223: Step 5 complete | L223: Step 7 | M223: G-00 | N223: Human-only | O223: Human-reserved
A224: R-0223 | B224: G-00 | C224: =IFERROR(INDEX('Agent Roster'!$B:$B,MATCH(B224,'Agent Roster'!$A:$A,0)),"UNASSIGNED") -> Founder / Operator (HUMAN) | D224: =IFERROR(INDEX('Agent Roster'!$D:$D,MATCH(B224,'Agent Roster'!$A:$A,0)),"UNASSIGNED") -> Governance & Meta-Tier | E224: ALG:Relationships Algorithm | F224: Step 7: Establish observation at multiple levels. The relationship persists when observed regularly across cognitive (memory), behavioral (action), emotional (attunement), and meaning (shared narrative) levels. | G224: Algorithm step | H224: Relationships Algorithm | I224: v5.1 L2807 | J224: — | K224: Step 6 complete | L224: Step 8 | M224: G-00 | N224: Human-only | O224: Human-reserved
A225: R-0224 | B225: G-00 | C225: =IFERROR(INDEX('Agent Roster'!$B:$B,MATCH(B225,'Agent Roster'!$A:$A,0)),"UNASSIGNED") -> Founder / Operator (HUMAN) | D225: =IFERROR(INDEX('Agent Roster'!$D:$D,MATCH(B225,'Agent Roster'!$A:$A,0)),"UNASSIGNED") -> Governance & Meta-Tier | E225: ALG:Relationships Algorithm | F225: Step 8: Per the Capsule mechanism: every prior interaction is integrated into the current relationship. Honor what has been built. Repair what has been damaged. | G225: Algorithm step | H225: Relationships Algorithm | I225: v5.1 L2809 | J225: — | K225: Step 7 complete | L225: Step 9 | M225: G-00 | N225: Human-only | O225: Human-reserved
A226: R-0225 | B226: G-00 | C226: =IFERROR(INDEX('Agent Roster'!$B:$B,MATCH(B226,'Agent Roster'!$A:$A,0)),"UNASSIGNED") -> Founder / Operator (HUMAN) | D226: =IFERROR(INDEX('Agent Roster'!$D:$D,MATCH(B226,'Agent Roster'!$A:$A,0)),"UNASSIGNED") -> Governance & Meta-Tier | E226: ALG:Relationships Algorithm | F226: Step 9: Per Documentation: durable agreements should be explicit, not assumed. | G226: Algorithm step | H226: Relationships Algorithm | I226: v5.1 L2811 | J226: — | K226: Step 8 complete | L226: Document & restart at higher baseline (Repetition) | M226: O-15 (Database) | N226: Human-only | O226: Human-reserved
A227: R-0226 | B227: G-00 | C227: =IFERROR(INDEX('Agent Roster'!$B:$B,MATCH(B227,'Agent Roster'!$A:$A,0)),"UNASSIGNED") -> Founder / Operator (HUMAN) | D227: =IFERROR(INDEX('Agent Roster'!$D:$D,MATCH(B227,'Agent Roster'!$A:$A,0)),"UNASSIGNED") -> Governance & Meta-Tier | E227: ALG:Health and Body Algorithm | F227: Step 1: Apply Three Kingdoms to the body. Third Kingdom (awareness, presence). Second Kingdom (nervous system, beliefs about body, habits). First Kingdom (physical structure, biochemistry, behavior). | G227: Algorithm step | H227: Health and Body Algorithm | I227: v5.1 L2817 | J227: — | K227: Algorithm triggered | L227: Step 2 | M227: G-00 | N227: Human-only | O227: Human-reserved
A228: R-0227 | B228: G-00 | C228: =IFERROR(INDEX('Agent Roster'!$B:$B,MATCH(B228,'Agent Roster'!$A:$A,0)),"UNASSIGNED") -> Founder / Operator (HUMAN) | D228: =IFERROR(INDEX('Agent Roster'!$D:$D,MATCH(B228,'Agent Roster'!$A:$A,0)),"UNASSIGNED") -> Governance & Meta-Tier | E228: ALG:Health and Body Algorithm | F228: Step 2: Identify the dynamic middle of the autonomic nervous system. Sympathetic (Yang — activate, perform) and parasympathetic (Yin — rest, restore) must alternate. Permanent Yang is burnout. Permanent Yin is depression and atrophy. | G228: Algorithm step | H228: Health and Body Algorithm | I228: v5.1 L2819 | J228: — | K228: Step 1 complete | L228: Step 3 | M228: G-00 | N228: Human-only | O228: Human-reserved
A229: R-0228 | B229: G-00 | C229: =IFERROR(INDEX('Agent Roster'!$B:$B,MATCH(B229,'Agent Roster'!$A:$A,0)),"UNASSIGNED") -> Founder / Operator (HUMAN) | D229: =IFERROR(INDEX('Agent Roster'!$D:$D,MATCH(B229,'Agent Roster'!$A:$A,0)),"UNASSIGNED") -> Governance & Meta-Tier | E229: ALG:Health and Body Algorithm | F229: Step 3: Apply Rhythm. Honor circadian, seasonal, weekly, and daily oscillations. Fighting biological rhythm produces compounding cost. | G229: Algorithm step | H229: Health and Body Algorithm | I229: v5.1 L2821 | J229: — | K229: Step 2 complete | L229: Step 4 | M229: G-00 | N229: Human-only | O229: Human-reserved
... A235: R-0234 | B235: G-00 | C235: =IFERROR(INDEX('Agent Roster'!$B:$B,MATCH(B235,'Agent Roster'!$A:$A,0)),"UNASSIGNED") -> Founder / Operator (HUMAN) | D235: =IFERROR(INDEX('Agent Roster'!$D:$D,MATCH(B235,'Agent Roster'!$A:$A,0)),"UNASSIGNED") -> Governance & Meta-Tier | E235: ALG:Health and Body Algorithm | F235: Step 9: Document patterns. The body sends signals; written tracking reveals patterns invisible in single moments. | G235: Algorithm step | H235: Health and Body Algorithm | I235: v5.1 L2833 | J235: — | K235: Step 8 complete | L235: Document & restart at higher baseline (Repetition) | M235: O-15 (Database) | N235: Human-only | O235: Human-reserved
A236: R-0235 | B236: FIN-01 | C236: =IFERROR(INDEX('Agent Roster'!$B:$B,MATCH(B236,'Agent Roster'!$A:$A,0)),"UNASSIGNED") -> Capital Manager | D236: =IFERROR(INDEX('Agent Roster'!$D:$D,MATCH(B236,'Agent Roster'!$A:$A,0)),"UNASSIGNED") -> 5 · Finance Hub | E236: ALG:Financial Decisions Algorithm | F236: Step 1: Identify which Kingdom the decision originates from. Reactive (First), strategic (Second), or vision-driven (Third). | G236: Algorithm step | H236: Financial Decisions Algorithm | I236: v5.1 L2839 | J236: Per capital decision; monthly review | K236: Algorithm triggered | L236: Step 2 | M236: FIN-01 | O236: Canon algorithm step
A237: R-0236 | B237: FIN-01 | C237: =IFERROR(INDEX('Agent Roster'!$B:$B,MATCH(B237,'Agent Roster'!$A:$A,0)),"UNASSIGNED") -> Capital Manager | D237: =IFERROR(INDEX('Agent Roster'!$D:$D,MATCH(B237,'Agent Roster'!$A:$A,0)),"UNASSIGNED") -> 5 · Finance Hub | E237: ALG:Financial Decisions Algorithm | F237: Step 2: Apply the Variable Principle ruthlessly. What is measurable? What are you assuming? | G237: Algorithm step | H237: Financial Decisions Algorithm | I237: v5.1 L2841 | J237: Per capital decision; monthly review | K237: Step 1 complete | L237: Step 3 | M237: FIN-01 | O237: Canon algorithm step
A238: R-0237 | B238: FIN-01 | C238: =IFERROR(INDEX('Agent Roster'!$B:$B,MATCH(B238,'Agent Roster'!$A:$A,0)),"UNASSIGNED") -> Capital Manager | D238: =IFERROR(INDEX('Agent Roster'!$D:$D,MATCH(B238,'Agent Roster'!$A:$A,0)),"UNASSIGNED") -> 5 · Finance Hub | E238: ALG:Financial Decisions Algorithm | F238: Step 3: Identify the gradient the financial decision channels. Opportunity gradient, risk gradient, liquidity gradient, growth gradient. | G238: Algorithm step | H238: Financial Decisions Algorithm | I238: v5.1 L2843 | J238: Per capital decision; monthly review | K238: Step 2 complete | L238: Step 4 | M238: FIN-01 | O238: Canon algorithm step
A239: R-0238 | B239: FIN-01 | C239: =IFERROR(INDEX('Agent Roster'!$B:$B,MATCH(B239,'Agent Roster'!$A:$A,0)),"UNASSIGNED") -> Capital Manager | D239: =IFERROR(INDEX('Agent Roster'!$D:$D,MATCH(B239,'Agent Roster'!$A:$A,0)),"UNASSIGNED") -> 5 · Finance Hub | E239: ALG:Financial Decisions Algorithm | F239: Step 4: Apply Process Density. Are you accumulating sufficient information density per dollar to make this decision well, or are you guessing? | G239: Algorithm step | H239: Financial Decisions Algorithm | I239: v5.1 L2845 | J239: Per capital decision; monthly review | K239: Step 3 complete | L239: Step 5 | M239: FIN-01 | O239: Canon algorithm step
A240: R-0239 | B240: FIN-01 | C240: =IFERROR(INDEX('Agent Roster'!$B:$B,MATCH(B240,'Agent Roster'!$A:$A,0)),"UNASSIGNED") -> Capital Manager | D240: =IFERROR(INDEX('Agent Roster'!$D:$D,MATCH(B240,'Agent Roster'!$A:$A,0)),"UNASSIGNED") -> 5 · Finance Hub | E240: ALG:Financial Decisions Algorithm | F240: Step 5: Run the falsifiability test. Under what conditions would this decision be wrong? At what threshold would you reverse? | G240: Algorithm step | H240: Financial Decisions Algorithm | I240: v5.1 L2847 | J240: Per capital decision; monthly review | K240: Step 4 complete | L240: Step 6 | M240: FIN-01 | O240: Canon algorithm step
A241: R-0240 | B241: FIN-01 | C241: =IFERROR(INDEX('Agent Roster'!$B:$B,MATCH(B241,'Agent Roster'!$A:$A,0)),"UNASSIGNED") -> Capital Manager | D241: =IFERROR(INDEX('Agent Roster'!$D:$D,MATCH(B241,'Agent Roster'!$A:$A,0)),"UNASSIGNED") -> 5 · Finance Hub | E241: ALG:Financial Decisions Algorithm | F241: Step 6: Locate the dynamic middle of risk. Conservative collapse fails to participate in growth. Aggressive collapse exposes to ruin. | G241: Algorithm step | H241: Financial Decisions Algorithm | I241: v5.1 L2849 | J241: Per capital decision; monthly review | K241: Step 5 complete | L241: Step 7 | M241: FIN-01 | O241: Canon algorithm step
A242: R-0241 | B242: FIN-01 | C242: =IFERROR(INDEX('Agent Roster'!$B:$B,MATCH(B242,'Agent Roster'!$A:$A,0)),"UNASSIGNED") -> Capital Manager | D242: =IFERROR(INDEX('Agent Roster'!$D:$D,MATCH(B242,'Agent Roster'!$A:$A,0)),"UNASSIGNED") -> 5 · Finance Hub | E242: ALG:Financial Decisions Algorithm | F242: Step 7: Apply Polarity. Profit and loss are poles of one axis — capital deployment. Eliminate neither; manage degree. | G242: Algorithm step | H242: Financial Decisions Algorithm | I242: v5.1 L2851 | J242: Per capital decision; monthly review | K242: Step 6 complete | L242: Step 8 | M242: FIN-01 | O242: Canon algorithm step
A243: R-0242 | B243: FIN-01 | C243: =IFERROR(INDEX('Agent Roster'!$B:$B,MATCH(B243,'Agent Roster'!$A:$A,0)),"UNASSIGNED") -> Capital Manager | D243: =IFERROR(INDEX('Agent Roster'!$D:$D,MATCH(B243,'Agent Roster'!$A:$A,0)),"UNASSIGNED") -> 5 · Finance Hub | E243: ALG:Financial Decisions Algorithm | F243: Step 8: Per Cause and Effect: every financial outcome traces to causes set earlier. Identify which causes set are still operating. | G243: Algorithm step | H243: Financial Decisions Algorithm | I243: v5.1 L2853 | J243: Per capital decision; monthly review | K243: Step 7 complete | L243: Step 9 | M243: FIN-01 | O243: Canon algorithm step
A244: R-0243 | B244: FIN-01 | C244: =IFERROR(INDEX('Agent Roster'!$B:$B,MATCH(B244,'Agent Roster'!$A:$A,0)),"UNASSIGNED") -> Capital Manager | D244: =IFERROR(INDEX('Agent Roster'!$D:$D,MATCH(B244,'Agent Roster'!$A:$A,0)),"UNASSIGNED") -> 5 · Finance Hub | E244: ALG:Financial Decisions Algorithm | F244: Step 9: Document the decision rationale, the variables, and the falsifiability conditions. | G244: Algorithm step | H244: Financial Decisions Algorithm | I244: v5.1 L2855 | J244: Per capital decision; monthly review | K244: Step 8 complete | L244: Step 10 | M244: FIN-01 | O244: Canon algorithm step
A245: R-0244 | B245: FIN-01 | C245: =IFERROR(INDEX('Agent Roster'!$B:$B,MATCH(B245,'Agent Roster'!$A:$A,0)),"UNASSIGNED") -> Capital Manager | D245: =IFERROR(INDEX('Agent Roster'!$D:$D,MATCH(B245,'Agent Roster'!$A:$A,0)),"UNASSIGNED") -> 5 · Finance Hub | E245: ALG:Financial Decisions Algorithm | F245: Step 10: Review monthly against outcomes. Integrate the gap per the Slime Mold mechanism. | G245: Algorithm step | H245: Financial Decisions Algorithm | I245: v5.1 L2857 | J245: Per capital decision; monthly review | K245: Step 9 complete | L245: Document & restart at higher baseline (Repetition) | M245: O-15 (Database) | O245: Canon algorithm step
A246: R-0245 | B246: O-22 | C246: =IFERROR(INDEX('Agent Roster'!$B:$B,MATCH(B246,'Agent Roster'!$A:$A,0)),"UNASSIGNED") -> Investigation & Research Agent | D246: =IFERROR(INDEX('Agent Roster'!$D:$D,MATCH(B246,'Agent Roster'!$A:$A,0)),"UNASSIGNED") -> Orchestration & Diagnostics | E246: ALG:Scientific Inquiry Algorithm | F246: Step 1: State the question with maximum precision. | G246: Algorithm step | H246: Scientific Inquiry Algorithm | I246: v5.1 L2867 | J246: Per Acquire-phase question | K246: Algorithm triggered | L246: Step 2 | M246: O-22 | O246: Canon algorithm step
A247: R-0246 | B247: O-22 | C247: =IFERROR(INDEX('Agent Roster'!$B:$B,MATCH(B247,'Agent Roster'!$A:$A,0)),"UNASSIGNED") -> Investigation & Research Agent | D247: =IFERROR(INDEX('Agent Roster'!$D:$D,MATCH(B247,'Agent Roster'!$A:$A,0)),"UNASSIGNED") -> Orchestration & Diagnostics | E247: ALG:Scientific Inquiry Algorithm | F247: Step 2: Identify what the answer would have to look like to count as an answer. What forms of response would qualify? | G247: Algorithm step | H247: Scientific Inquiry Algorithm | I247: v5.1 L2869 | J247: Per Acquire-phase question | K247: Step 1 complete | L247: Step 3 | M247: O-22 | O247: Canon algorithm step
... A329: R-0328 | B329: CON-05 | C329: =IFERROR(INDEX('Agent Roster'!$B:$B,MATCH(B329,'Agent Roster'!$A:$A,0)),"UNASSIGNED") -> GFunnel University Curriculum Agent | D329: =IFERROR(INDEX('Agent Roster'!$D:$D,MATCH(B329,'Agent Roster'!$A:$A,0)),"UNASSIGNED") -> 9 · Content Hub | E329: ALG:Teaching and Mentoring Algorithm | F329: Step 10: Per Repetition: each cycle of teaching is from a higher baseline. | G329: Algorithm step | H329: Teaching and Mentoring Algorithm | I329: v5.1 L3069 | J329: Per course / mentoring cycle | K329: Step 9 complete | L329: Document & restart at higher baseline (Repetition) | M329: O-15 (Database) | O329: Canon algorithm step
A330: R-0329 | B330: G-00 | C330: =IFERROR(INDEX('Agent Roster'!$B:$B,MATCH(B330,'Agent Roster'!$A:$A,0)),"UNASSIGNED") -> Founder / Operator (HUMAN) | D330: =IFERROR(INDEX('Agent Roster'!$D:$D,MATCH(B330,'Agent Roster'!$A:$A,0)),"UNASSIGNED") -> Governance & Meta-Tier | E330: ALG:Domain 1 — Spiritual Process Algorithm | F330: Step 1: Detect the suffering, incompleteness, or intuition that something foundational is being missed. | G330: Algorithm step | H330: Domain 1 — Spiritual Process Algorithm | I330: v5.1 L3079 | J330: — | K330: Algorithm triggered | L330: Step 2 | M330: G-00 | N330: Human-only | O330: Human-reserved
A331: R-0330 | B331: G-00 | C331: =IFERROR(INDEX('Agent Roster'!$B:$B,MATCH(B331,'Agent Roster'!$A:$A,0)),"UNASSIGNED") -> Founder / Operator (HUMAN) | D331: =IFERROR(INDEX('Agent Roster'!$D:$D,MATCH(B331,'Agent Roster'!$A:$A,0)),"UNASSIGNED") -> Governance & Meta-Tier | E331: ALG:Domain 1 — Spiritual Process Algorithm | F331: Step 2: Locate the contrast that produced the recognition. Per Layer I.C Domain 1: separation is the precondition for recognition of the Third Kingdom. | G331: Algorithm step | H331: Domain 1 — Spiritual Process Algorithm | I331: v5.1 L3081 | J331: — | K331: Step 1 complete | L331: Step 3 | M331: G-00 | N331: Human-only | O331: Human-reserved
A332: R-0331 | B332: G-00 | C332: =IFERROR(INDEX('Agent Roster'!$B:$B,MATCH(B332,'Agent Roster'!$A:$A,0)),"UNASSIGNED") -> Founder / Operator (HUMAN) | D332: =IFERROR(INDEX('Agent Roster'!$D:$D,MATCH(B332,'Agent Roster'!$A:$A,0)),"UNASSIGNED") -> Governance & Meta-Tier | E332: ALG:Domain 1 — Spiritual Process Algorithm | F332: Step 3: Establish a deliberate practice. Meditation, prayer, contemplation, service, direct inquiry. | G332: Algorithm step | H332: Domain 1 — Spiritual Process Algorithm | I332: v5.1 L3083 | J332: — | K332: Step 2 complete | L332: Step 4 | M332: G-00 | N332: Human-only | O332: Human-reserved
A333: R-0332 | B333: G-00 | C333: =IFERROR(INDEX('Agent Roster'!$B:$B,MATCH(B333,'Agent Roster'!$A:$A,0)),"UNASSIGNED") -> Founder / Operator (HUMAN) | D333: =IFERROR(INDEX('Agent Roster'!$D:$D,MATCH(B333,'Agent Roster'!$A:$A,0)),"UNASSIGNED") -> Governance & Meta-Tier | E333: ALG:Domain 1 — Spiritual Process Algorithm | F333: Step 4: Apply the practice consistently. Per Process Density: insight emerges at threshold density of practice, not from a single session. | G333: Algorithm step | H333: Domain 1 — Spiritual Process Algorithm | I333: v5.1 L3085 | J333: — | K333: Step 3 complete | L333: Step 5 | M333: G-00 | N333: Human-only | O333: Human-reserved
A334: R-0333 | B334: G-00 | C334: =IFERROR(INDEX('Agent Roster'!$B:$B,MATCH(B334,'Agent Roster'!$A:$A,0)),"UNASSIGNED") -> Founder / Operator (HUMAN) | D334: =IFERROR(INDEX('Agent Roster'!$D:$D,MATCH(B334,'Agent Roster'!$A:$A,0)),"UNASSIGNED") -> Governance & Meta-Tier | E334: ALG:Domain 1 — Spiritual Process Algorithm | F334: Step 5: Observe the integration without grasping. Per Layer I.D: the dynamic middle of spiritual work is engagement without attachment. | G334: Algorithm step | H334: Domain 1 — Spiritual Process Algorithm | I334: v5.1 L3087 | J334: — | K334: Step 4 complete | L334: Step 6 | M334: G-00 | N334: Human-only | O334: Human-reserved
A335: R-0334 | B335: G-00 | C335: =IFERROR(INDEX('Agent Roster'!$B:$B,MATCH(B335,'Agent Roster'!$A:$A,0)),"UNASSIGNED") -> Founder / Operator (HUMAN) | D335: =IFERROR(INDEX('Agent Roster'!$D:$D,MATCH(B335,'Agent Roster'!$A:$A,0)),"UNASSIGNED") -> Governance & Meta-Tier | E335: ALG:Domain 1 — Spiritual Process Algorithm | F335: Step 6: Document insights. Per Propagation Mode 3: spiritual experience that is not articulated returns repeatedly at full cost. | G335: Algorithm step | H335: Domain 1 — Spiritual Process Algorithm | I335: v5.1 L3089 | J335: — | K335: Step 5 complete | L335: Step 7 | M335: G-00 | N335: Human-only | O335: Human-reserved
A336: R-0335 | B336: G-00 | C336: =IFERROR(INDEX('Agent Roster'!$B:$B,MATCH(B336,'Agent Roster'!$A:$A,0)),"UNASSIGNED") -> Founder / Operator (HUMAN) | D336: =IFERROR(INDEX('Agent Roster'!$D:$D,MATCH(B336,'Agent Roster'!$A:$A,0)),"UNASSIGNED") -> Governance & Meta-Tier | E336: ALG:Domain 1 — Spiritual Process Algorithm | F336: Step 7: Per Repetition: each cycle restarts at a higher baseline. Per Fibonacci: each cycle is informed by the two prior. | G336: Algorithm step | H336: Domain 1 — Spiritual Process Algorithm | I336: v5.1 L3091 | J336: — | K336: Step 6 complete | L336: Step 8 | M336: G-00 | N336: Human-only | O336: Human-reserved
A337: R-0336 | B337: G-00 | C337: =IFERROR(INDEX('Agent Roster'!$B:$B,MATCH(B337,'Agent Roster'!$A:$A,0)),"UNASSIGNED") -> Founder / Operator (HUMAN) | D337: =IFERROR(INDEX('Agent Roster'!$D:$D,MATCH(B337,'Agent Roster'!$A:$A,0)),"UNASSIGNED") -> Governance & Meta-Tier | E337: ALG:Domain 1 — Spiritual Process Algorithm | F337: Step 8: Per Vibration: at higher integration, share with frequency-matched receivers. Forced sharing dissipates. | G337: Algorithm step | H337: Domain 1 — Spiritual Process Algorithm | I337: v5.1 L3093 | J337: — | K337: Step 7 complete | L337: Document & restart at higher baseline (Repetition) | M337: O-15 (Database) | N337: Human-only | O337: Human-reserved
A338: R-0337 | B338: G-00 | C338: =IFERROR(INDEX('Agent Roster'!$B:$B,MATCH(B338,'Agent Roster'!$A:$A,0)),"UNASSIGNED") -> Founder / Operator (HUMAN) | D338: =IFERROR(INDEX('Agent Roster'!$D:$D,MATCH(B338,'Agent Roster'!$A:$A,0)),"UNASSIGNED") -> Governance & Meta-Tier | E338: ALG:Domain 2 — Religious Process Algorithm | F338: Step 1: Identify the founding signal. What core revelation, principle, or recognition is the tradition built around? | G338: Algorithm step | H338: Domain 2 — Religious Process Algorithm | I338: v5.1 L3099 | J338: — | K338: Algorithm triggered | L338: Step 2 | M338: G-00 | N338: Human-only | O338: Human-reserved
A339: R-0338 | B339: G-00 | C339: =IFERROR(INDEX('Agent Roster'!$B:$B,MATCH(B339,'Agent Roster'!$A:$A,0)),"UNASSIGNED") -> Founder / Operator (HUMAN) | D339: =IFERROR(INDEX('Agent Roster'!$D:$D,MATCH(B339,'Agent Roster'!$A:$A,0)),"UNASSIGNED") -> Governance & Meta-Tier | E339: ALG:Domain 2 — Religious Process Algorithm | F339: Step 2: Identify the doctrine that codifies the signal. Per Vibration: codification is necessary but always degrades the signal somewhat. | G339: Algorithm step | H339: Domain 2 — Religious Process Algorithm | I339: v5.1 L3101 | J339: — | K339: Step 1 complete | L339: Step 3 | M339: G-00 | N339: Human-only | O339: Human-reserved
A340: R-0339 | B340: G-00 | C340: =IFERROR(INDEX('Agent Roster'!$B:$B,MATCH(B340,'Agent Roster'!$A:$A,0)),"UNASSIGNED") -> Founder / Operator (HUMAN) | D340: =IFERROR(INDEX('Agent Roster'!$D:$D,MATCH(B340,'Agent Roster'!$A:$A,0)),"UNASSIGNED") -> Governance & Meta-Tier | E340: ALG:Domain 2 — Religious Process Algorithm | F340: Step 3: Identify the institutional structures that propagate the codified doctrine. | G340: Algorithm step | H340: Domain 2 — Religious Process Algorithm | I340: v5.1 L3103 | J340: — | K340: Step 2 complete | L340: Step 4 | M340: G-00 | N340: Human-only | O340: Human-reserved
A341: R-0340 | B341: G-00 | C341: =IFERROR(INDEX('Agent Roster'!$B:$B,MATCH(B341,'Agent Roster'!$A:$A,0)),"UNASSIGNED") -> Founder / Operator (HUMAN) | D341: =IFERROR(INDEX('Agent Roster'!$D:$D,MATCH(B341,'Agent Roster'!$A:$A,0)),"UNASSIGNED") -> Governance & Meta-Tier | E341: ALG:Domain 2 — Religious Process Algorithm | F341: Step 4: Apply Falsifiability test. What in the tradition is empirically testable? What is structurally claimed? What is held as variable? | G341: Algorithm step | H341: Domain 2 — Religious Process Algorithm | I341: v5.1 L3105 | J341: — | K341: Step 3 complete | L341: Step 5 | M341: G-00 | N341: Human-only | O341: Human-reserved
... A354: R-0353 | B354: G-00 | C354: =IFERROR(INDEX('Agent Roster'!$B:$B,MATCH(B354,'Agent Roster'!$A:$A,0)),"UNASSIGNED") -> Founder / Operator (HUMAN) | D354: =IFERROR(INDEX('Agent Roster'!$D:$D,MATCH(B354,'Agent Roster'!$A:$A,0)),"UNASSIGNED") -> Governance & Meta-Tier | E354: ALG:Domain 3 — Psychological Process Algorithm | F354: Step 9: Per Repetition: each cycle integrates prior cycles. Healing is compound. | G354: Algorithm step | H354: Domain 3 — Psychological Process Algorithm | I354: v5.1 L3135 | J354: — | K354: Step 8 complete | L354: Document & restart at higher baseline (Repetition) | M354: O-15 (Database) | N354: Human-only | O354: Human-reserved
A355: R-0354 | B355: O-01 | C355: =IFERROR(INDEX('Agent Roster'!$B:$B,MATCH(B355,'Agent Roster'!$A:$A,0)),"UNASSIGNED") -> Intake & Triage Agent (Layer 0 Base Code) | D355: =IFERROR(INDEX('Agent Roster'!$D:$D,MATCH(B355,'Agent Roster'!$A:$A,0)),"UNASSIGNED") -> Orchestration & Diagnostics | E355: ALG:Domain 4 — Matrix / Information Process Algorithm | F355: Step 1: Identify which kind of matrix process you are operating within: simulation/computational, social/conditioning, or information theoretic. | G355: Algorithm step | H355: Domain 4 — Matrix / Information Process Algorithm | I355: v5.1 L3141 | J355: Per input surge | K355: Algorithm triggered | L355: Step 2 | M355: O-01 | O355: Canon algorithm step
A356: R-0355 | B356: O-01 | C356: =IFERROR(INDEX('Agent Roster'!$B:$B,MATCH(B356,'Agent Roster'!$A:$A,0)),"UNASSIGNED") -> Intake & Triage Agent (Layer 0 Base Code) | D356: =IFERROR(INDEX('Agent Roster'!$D:$D,MATCH(B356,'Agent Roster'!$A:$A,0)),"UNASSIGNED") -> Orchestration & Diagnostics | E356: ALG:Domain 4 — Matrix / Information Process Algorithm | F356: Step 2: For computational: identify the substrate, the rules, and the rendered output. | G356: Algorithm step | H356: Domain 4 — Matrix / Information Process Algorithm | I356: v5.1 L3143 | J356: Per input surge | K356: Step 1 complete | L356: Step 3 | M356: O-01 | O356: Canon algorithm step
A357: R-0356 | B357: O-01 | C357: =IFERROR(INDEX('Agent Roster'!$B:$B,MATCH(B357,'Agent Roster'!$A:$A,0)),"UNASSIGNED") -> Intake & Triage Agent (Layer 0 Base Code) | D357: =IFERROR(INDEX('Agent Roster'!$D:$D,MATCH(B357,'Agent Roster'!$A:$A,0)),"UNASSIGNED") -> Orchestration & Diagnostics | E357: ALG:Domain 4 — Matrix / Information Process Algorithm | F357: Step 3: For social conditioning: identify which Second Kingdom narratives are being presented as First Kingdom reality. | G357: Algorithm step | H357: Domain 4 — Matrix / Information Process Algorithm | I357: v5.1 L3145 | J357: Per input surge | K357: Step 2 complete | L357: Step 4 | M357: O-01 | O357: Canon algorithm step
A358: R-0357 | B358: O-01 | C358: =IFERROR(INDEX('Agent Roster'!$B:$B,MATCH(B358,'Agent Roster'!$A:$A,0)),"UNASSIGNED") -> Intake & Triage Agent (Layer 0 Base Code) | D358: =IFERROR(INDEX('Agent Roster'!$D:$D,MATCH(B358,'Agent Roster'!$A:$A,0)),"UNASSIGNED") -> Orchestration & Diagnostics | E358: ALG:Domain 4 — Matrix / Information Process Algorithm | F358: Step 4: Apply the Variable Principle. What in the conditioning has been filled with assumption rather than measured? | G358: Algorithm step | H358: Domain 4 — Matrix / Information Process Algorithm | I358: v5.1 L3147 | J358: Per input surge | K358: Step 3 complete | L358: Step 5 | M358: O-01 | O358: Canon algorithm step
A359: R-0358 | B359: O-01 | C359: =IFERROR(INDEX('Agent Roster'!$B:$B,MATCH(B359,'Agent Roster'!$A:$A,0)),"UNASSIGNED") -> Intake & Triage Agent (Layer 0 Base Code) | D359: =IFERROR(INDEX('Agent Roster'!$D:$D,MATCH(B359,'Agent Roster'!$A:$A,0)),"UNASSIGNED") -> Orchestration & Diagnostics | E359: ALG:Domain 4 — Matrix / Information Process Algorithm | F359: Step 5: The red-pill moment is the recognition of an assumption-as-variable. Hold it open, do not refill with the opposite assumption. | G359: Algorithm step | H359: Domain 4 — Matrix / Information Process Algorithm | I359: v5.1 L3149 | J359: Per input surge | K359: Step 4 complete | L359: Step 6 | M359: O-01 | O359: Canon algorithm step
A360: R-0359 | B360: O-01 | C360: =IFERROR(INDEX('Agent Roster'!$B:$B,MATCH(B360,'Agent Roster'!$A:$A,0)),"UNASSIGNED") -> Intake & Triage Agent (Layer 0 Base Code) | D360: =IFERROR(INDEX('Agent Roster'!$D:$D,MATCH(B360,'Agent Roster'!$A:$A,0)),"UNASSIGNED") -> Orchestration & Diagnostics | E360: ALG:Domain 4 — Matrix / Information Process Algorithm | F360: Step 6: For information theoretic: quantify the entropy. Per Shannon: information is resolved variability. | G360: Algorithm step | H360: Domain 4 — Matrix / Information Process Algorithm | I360: v5.1 L3151 | J360: Per input surge | K360: Step 5 complete | L360: Step 7 | M360: O-01 | O360: Canon algorithm step
A361: R-0360 | B361: O-01 | C361: =IFERROR(INDEX('Agent Roster'!$B:$B,MATCH(B361,'Agent Roster'!$A:$A,0)),"UNASSIGNED") -> Intake & Triage Agent (Layer 0 Base Code) | D361: =IFERROR(INDEX('Agent Roster'!$D:$D,MATCH(B361,'Agent Roster'!$A:$A,0)),"UNASSIGNED") -> Orchestration & Diagnostics | E361: ALG:Domain 4 — Matrix / Information Process Algorithm | F361: Step 7: Direct attention deliberately. Per Multi-Level Observation: what is observed persists and shapes further input processing. | G361: Algorithm step | H361: Domain 4 — Matrix / Information Process Algorithm | I361: v5.1 L3153 | J361: Per input surge | K361: Step 6 complete | L361: Step 8 | M361: O-01 | O361: Canon algorithm step
A362: R-0361 | B362: O-01 | C362: =IFERROR(INDEX('Agent Roster'!$B:$B,MATCH(B362,'Agent Roster'!$A:$A,0)),"UNASSIGNED") -> Intake & Triage Agent (Layer 0 Base Code) | D362: =IFERROR(INDEX('Agent Roster'!$D:$D,MATCH(B362,'Agent Roster'!$A:$A,0)),"UNASSIGNED") -> Orchestration & Diagnostics | E362: ALG:Domain 4 — Matrix / Information Process Algorithm | F362: Step 8: Document the structural learning. Per Database step. | G362: Algorithm step | H362: Domain 4 — Matrix / Information Process Algorithm | I362: v5.1 L3155 | J362: Per input surge | K362: Step 7 complete | L362: Document & restart at higher baseline (Repetition) | M362: O-15 (Database) | O362: Canon algorithm step
A363: R-0362 | B363: O-22 | C363: =IFERROR(INDEX('Agent Roster'!$B:$B,MATCH(B363,'Agent Roster'!$A:$A,0)),"UNASSIGNED") -> Investigation & Research Agent | D363: =IFERROR(INDEX('Agent Roster'!$D:$D,MATCH(B363,'Agent Roster'!$A:$A,0)),"UNASSIGNED") -> Orchestration & Diagnostics | E363: ALG:Domain 5 — Mathematical / Computational Process Algorithm | F363: Step 1: State the axioms or premises with maximum clarity. | G363: Algorithm step | H363: Domain 5 — Mathematical / Computational Process Algorithm | I363: v5.1 L3161 | J363: Per analysis | K363: Algorithm triggered | L363: Step 2 | M363: O-22 | O363: Canon algorithm step
A364: R-0363 | B364: O-22 | C364: =IFERROR(INDEX('Agent Roster'!$B:$B,MATCH(B364,'Agent Roster'!$A:$A,0)),"UNASSIGNED") -> Investigation & Research Agent | D364: =IFERROR(INDEX('Agent Roster'!$D:$D,MATCH(B364,'Agent Roster'!$A:$A,0)),"UNASSIGNED") -> Orchestration & Diagnostics | E364: ALG:Domain 5 — Mathematical / Computational Process Algorithm | F364: Step 2: Apply the rules of inference rigorously. No assumed steps. | G364: Algorithm step | H364: Domain 5 — Mathematical / Computational Process Algorithm | I364: v5.1 L3163 | J364: Per analysis | K364: Step 1 complete | L364: Step 3 | M364: O-22 | O364: Canon algorithm step
A365: R-0364 | B365: O-22 | C365: =IFERROR(INDEX('Agent Roster'!$B:$B,MATCH(B365,'Agent Roster'!$A:$A,0)),"UNASSIGNED") -> Investigation & Research Agent | D365: =IFERROR(INDEX('Agent Roster'!$D:$D,MATCH(B365,'Agent Roster'!$A:$A,0)),"UNASSIGNED") -> Orchestration & Diagnostics | E365: ALG:Domain 5 — Mathematical / Computational Process Algorithm | F365: Step 3: Per Recursion: a function that calls itself produces compounding behavior. Use deliberately. | G365: Algorithm step | H365: Domain 5 — Mathematical / Computational Process Algorithm | I365: v5.1 L3165 | J365: Per analysis | K365: Step 2 complete | L365: Step 4 | M365: O-22 | O365: Canon algorithm step
A366: R-0365 | B366: O-22 | C366: =IFERROR(INDEX('Agent Roster'!$B:$B,MATCH(B366,'Agent Roster'!$A:$A,0)),"UNASSIGNED") -> Investigation & Research Agent | D366: =IFERROR(INDEX('Agent Roster'!$D:$D,MATCH(B366,'Agent Roster'!$A:$A,0)),"UNASSIGNED") -> Orchestration & Diagnostics | E366: ALG:Domain 5 — Mathematical / Computational Process Algorithm | F366: Step 4: Per Emergence: simple rules at sufficient density produce complex behavior. Conway’s Game of Life as the canonical example. | G366: Algorithm step | H366: Domain 5 — Mathematical / Computational Process Algorithm | I366: v5.1 L3167 | J366: Per analysis | K366: Step 3 complete | L366: Step 5 | M366: O-22 | O366: Canon algorithm step
... A423: R-0422 | B423: O-19 | C423: =IFERROR(INDEX('Agent Roster'!$B:$B,MATCH(B423,'Agent Roster'!$A:$A,0)),"UNASSIGNED") -> Crisis Coordinator | D423: =IFERROR(INDEX('Agent Roster'!$D:$D,MATCH(B423,'Agent Roster'!$A:$A,0)),"UNASSIGNED") -> Orchestration & Diagnostics | E423: ALG:Crisis Response Algorithm | F423: Step 2: Stop the bleeding. Address First Kingdom physical impact before processing causes. | G423: Algorithm step | H423: Crisis Response Algorithm | I423: v5.1 L3388 | J423: Per crisis | K423: Step 1 complete | L423: Step 3 | M423: O-19 | O423: Canon algorithm step
A424: R-0423 | B424: G-00 | C424: =IFERROR(INDEX('Agent Roster'!$B:$B,MATCH(B424,'Agent Roster'!$A:$A,0)),"UNASSIGNED") -> Founder / Operator (HUMAN) | D424: =IFERROR(INDEX('Agent Roster'!$D:$D,MATCH(B424,'Agent Roster'!$A:$A,0)),"UNASSIGNED") -> Governance & Meta-Tier | E424: ALG:Crisis Response Algorithm | F424: Step 3: Centralize command. Per Mentalism: in crisis, decision-making must converge to a clear Third Kingdom locus. Distributed reactive decisions amplify the crisis. | G424: Algorithm step | H424: Crisis Response Algorithm | I424: v5.1 L3390 | J424: Per crisis | K424: Step 2 complete | L424: Step 4 | M424: G-00 | N424: Human-only | O424: Canon algorithm step
A425: R-0424 | B425: O-19 | C425: =IFERROR(INDEX('Agent Roster'!$B:$B,MATCH(B425,'Agent Roster'!$A:$A,0)),"UNASSIGNED") -> Crisis Coordinator | D425: =IFERROR(INDEX('Agent Roster'!$D:$D,MATCH(B425,'Agent Roster'!$A:$A,0)),"UNASSIGNED") -> Orchestration & Diagnostics | E425: ALG:Crisis Response Algorithm | F425: Step 4: Establish the gradient between current state and acceptable state. The gradient is what the response will channel. | G425: Algorithm step | H425: Crisis Response Algorithm | I425: v5.1 L3392 | J425: Per crisis | K425: Step 3 complete | L425: Step 5 | M425: O-19 | O425: Canon algorithm step
...

Sheet Algorithm Coverage
A1: Algorithm | B1: Category | C1: Steps in Canon (parsed) | D1: Steps Mapped | E1: Unmapped | F1: Canon Location | G1: Primary Owner | H1: All Owners | I1: Coverage Status | J1: Cadence
A2: Master Meta-Algorithm | B2: Meta | C2: 12 | D2: =COUNTIFS(Responsibilities!$H:$H,A2,Responsibilities!$G:$G,"Algorithm step") -> 12 | E2: =C2-D2 -> 0 | F2: v5.1 L2178–2203 | G2: O-02 | H2: O-02 | I2: Assigned | J2: Per un-routed problem
A3: Layer 0 — The Base Code Algorithm | B3: Per-layer | C3: 6 | D3: =COUNTIFS(Responsibilities!$H:$H,A3,Responsibilities!$G:$G,"Algorithm step") -> 6 | E3: =C3-D3 -> 0 | F3: v5.1 L2232–2247 | G3: O-01 | H3: O-01 | I3: Assigned | J3: Per input
A4: Layer I — The Three Kingdoms Identification Algorithm | B4: Per-layer | C4: 7 | D4: =COUNTIFS(Responsibilities!$H:$H,A4,Responsibilities!$G:$G,"Algorithm step") -> 7 | E4: =C4-D4 -> 0 | F4: v5.1 L2250–2267 | G4: O-05 | H4: O-05 | I4: Assigned | J4: Per diagnosis
A5: Layer I.B — The Civil Infrastructure Algorithm | B5: Per-layer | C5: 7 | D5: =COUNTIFS(Responsibilities!$H:$H,A5,Responsibilities!$G:$G,"Algorithm step") -> 7 | E5: =C5-D5 -> 0 | F5: v5.1 L2270–2287 | G5: O-11 | H5: O-11 | I5: Assigned | J5: Before each scale move
A6: Layer I.C — The Universal Process Registry Algorithm | B6: Per-layer | C6: 7 | D6: =COUNTIFS(Responsibilities!$H:$H,A6,Responsibilities!$G:$G,"Algorithm step") -> 7 | E6: =C6-D6 -> 0 | F6: v5.1 L2290–2307 | G6: O-12 | H6: O-12 | I6: Assigned | J6: Per unfamiliar process
A7: Layer I.D — The Yin/Yang Dynamic Middle Algorithm | B7: Per-layer | C7: 8 | D7: =COUNTIFS(Responsibilities!$H:$H,A7,Responsibilities!$G:$G,"Algorithm step") -> 8 | E7: =C7-D7 -> 0 | F7: v5.1 L2310–2329 | G7: O-07 | H7: O-07 | I7: Assigned | J7: Continuous / monthly
A8: Layer I.E — The Energy Continuation Algorithm | B8: Per-layer | C8: 8 | D8: =COUNTIFS(Responsibilities!$H:$H,A8,Responsibilities!$G:$G,"Algorithm step") -> 8 | E8: =C8-D8 -> 0 | F8: v5.1 L2332–2351 | G8: O-08 | H8: O-08 | I8: Assigned | J8: Per stall
A9: Layer I.F — The Multi-Level Observation Algorithm | B9: Per-layer | C9: 7 | D9: =COUNTIFS(Responsibilities!$H:$H,A9,Responsibilities!$G:$G,"Algorithm step") -> 7 | E9: =C9-D9 -> 0 | F9: v5.1 L2354–2371 | G9: O-09 | H9: O-09 | I9: Assigned | J9: Per asset that must persist
A10: Layer I.G — The Slime Mold Integration Algorithm | B10: Per-layer | C10: 7 | D10: =COUNTIFS(Responsibilities!$H:$H,A10,Responsibilities!$G:$G,"Algorithm step") -> 7 | E10: =C10-D10 -> 0 | F10: v5.1 L2374–2391 | G10: O-10 | H10: O-10 | I10: Assigned | J10: Per failure
A11: Layer II — The Seven Hermetic Principles Algorithm | B11: Per-layer | C11: 9 | D11: =COUNTIFS(Responsibilities!$H:$H,A11,Responsibilities!$G:$G,"Algorithm step") -> 9 | E11: =C11-D11 -> 0 | F11: v5.1 L2394–2415 | G11: O-06 | H11: O-06 | I11: Assigned | J11: Per failure diagnosis
A12: Layer III — The Process Density Algorithm | B12: Per-layer | C12: 7 | D12: =COUNTIFS(Responsibilities!$H:$H,A12,Responsibilities!$G:$G,"Algorithm step") -> 7 | E12: =C12-D12 -> 0 | F12: v5.1 L2418–2435 | G12: O-13 | H12: O-13 | I12: Assigned | J12: Per system design review
A13: Layer III+ — The Integration Density Algorithm | B13: Per-layer | C13: 7 | D13: =COUNTIFS(Responsibilities!$H:$H,A13,Responsibilities!$G:$G,"Algorithm step") -> 7 | E13: =C13-D13 -> 0 | F13: v5.1 L2438–2455 | G13: O-14 | H13: O-14 | I13: Assigned | J13: Per cycle kickoff
... A78: Ecological Restoration Algorithm | B78: Extended governance | C78: 8 | D78: =COUNTIFS(Responsibilities!$H:$H,A78,Responsibilities!$G:$G,"Algorithm step") -> 8 | E78: =C78-D78 -> 0 | F78: v5.1 L3979–3996 | G78: G-00 | H78: G-00 | I78: Out of scope for a non-ecological business (human-reserved) | J78: —
A80: 'Steps in Canon' is parsed from versions/v5.1 by build_agent_map.py (numbered lines inside each algorithm section). Canon's Fast-Reference index lists 48 algorithm rows (its footer says 47); the Extended section adds 29 → 77, matching canon's '70+'.

Sheet Canon Element Coverage
A1: Element Key | B1: Canon Element | C1: Source | D1: Canon Location | E1: Owner Agent | F1: Responsibilities Mapped | G1: Covered?
A2: DEPT:STR:Vision | B2: Own the 'Vision' function of the 1 · Strategy Hub (Constitution + founding law). | C2: Nine Departments map — primary function | D2: v5.1 L1378 | E2: STR-01 | F2: =COUNTIF(Responsibilities!$E:$E,A2) -> 1 | G2: =IF(F2>0,"YES","GAP") -> YES
A3: DEPT:STR:Mission | B3: Own the 'Mission' function of the 1 · Strategy Hub (Constitution + founding law). | C3: Nine Departments map — primary function | D3: v5.1 L1378 | E3: STR-01 | F3: =COUNTIF(Responsibilities!$E:$E,A3) -> 1 | G3: =IF(F3>0,"YES","GAP") -> YES
A4: DEPT:STR:Values | B4: Own the 'Values' function of the 1 · Strategy Hub (Constitution + founding law). | C4: Nine Departments map — primary function | D4: v5.1 L1378 | E4: STR-02 | F4: =COUNTIF(Responsibilities!$E:$E,A4) -> 1 | G4: =IF(F4>0,"YES","GAP") -> YES
A5: DEPT:STR:Governing principles | B5: Own the 'Governing principles' function of the 1 · Strategy Hub (Constitution + founding law). | C5: Nine Departments map — primary function | D5: v5.1 L1378 | E5: STR-02 | F5: =COUNTIF(Responsibilities!$E:$E,A5) -> 1 | G5: =IF(F5>0,"YES","GAP") -> YES
A6: DEPT:STR:Quarterly direction | B6: Own the 'Quarterly direction' function of the 1 · Strategy Hub (Constitution + founding law). | C6: Nine Departments map — primary function | D6: v5.1 L1378 | E6: STR-03 | F6: =COUNTIF(Responsibilities!$E:$E,A6) -> 1 | G6: =IF(F6>0,"YES","GAP") -> YES
A7: DEPT:STR:Competitive positioning | B7: Own the 'Competitive positioning' function of the 1 · Strategy Hub (Constitution + founding law). | C7: Nine Departments map — primary function | D7: v5.1 L1378 | E7: STR-04 | F7: =COUNTIF(Responsibilities!$E:$E,A7) -> 1 | G7: =IF(F7>0,"YES","GAP") -> YES
A8: DEPT:STR:BEAS-row | B8: Self-score the 1 · Strategy Hub on Correctness, Complexity, Patience, Resilience (0 / 0.5 / 1 each) with evidence, and score coordination with the other eight hubs (0–1). | C8: BEAS Scoring Instructions | D8: v5.1 L1396–1404 | E8: STR-00 | F8: =COUNTIF(Responsibilities!$E:$E,A8) -> 1 | G8: =IF(F8>0,"YES","GAP") -> YES
A9: DEPT:MKT:Lead generation | B9: Own the 'Lead generation' function of the 2 · Marketing Hub (Roads + traffic systems). | C9: Nine Departments map — primary function | D9: v5.1 L1379 | E9: MKT-01 | F9: =COUNTIF(Responsibilities!$E:$E,A9) -> 1 | G9: =IF(F9>0,"YES","GAP") -> YES
A10: DEPT:MKT:Traffic | B10: Own the 'Traffic' function of the 2 · Marketing Hub (Roads + traffic systems). | C10: Nine Departments map — primary function | D10: v5.1 L1379 | E10: MKT-02 | F10: =COUNTIF(Responsibilities!$E:$E,A10) -> 1 | G10: =IF(F10>0,"YES","GAP") -> YES
A11: DEPT:MKT:Attention | B11: Own the 'Attention' function of the 2 · Marketing Hub (Roads + traffic systems). | C11: Nine Departments map — primary function | D11: v5.1 L1379 | E11: MKT-03 | F11: =COUNTIF(Responsibilities!$E:$E,A11) -> 1 | G11: =IF(F11>0,"YES","GAP") -> YES
A12: DEPT:MKT:Brand awareness | B12: Own the 'Brand awareness' function of the 2 · Marketing Hub (Roads + traffic systems). | C12: Nine Departments map — primary function | D12: v5.1 L1379 | E12: MKT-04 | F12: =COUNTIF(Responsibilities!$E:$E,A12) -> 1 | G12: =IF(F12>0,"YES","GAP") -> YES
A13: DEPT:MKT:Content distribution | B13: Own the 'Content distribution' function of the 2 · Marketing Hub (Roads + traffic systems). | C13: Nine Departments map — primary function | D13: v5.1 L1379 | E13: MKT-05 | F13: =COUNTIF(Responsibilities!$E:$E,A13) -> 1 | G13: =IF(F13>0,"YES","GAP") -> YES
... A183: UPDATE:Protocol | B183: Document Update Protocol: when evidence narrows a business variable, record the narrowing, the newly opened variables, and load it as substrate for the next cycle (never silently overwrite). | C183: Document Update Protocol | D183: v5.1 L204–222 | E183: G-01 | F183: =COUNTIF(Responsibilities!$E:$E,A183) -> 1 | G183: =IF(F183>0,"YES","GAP") -> YES

Sheet BEAS Accountability
A1: BEAS — Business Equilibrium Adherence Score (45-point monthly assessment)
A2: Yellow cells: enter 0 (absent), 0.5 (partial) or 1 (fully implemented); coordination 0–1. Row 16 is an illustrative EXAMPLE and is not counted. Source: v5.1 L1389–1446.
A4: Department | B4: Accountable Lead | C4: Correctness | D4: Correctness Agent | E4: Complexity | F4: Complexity Agent | G4: Patience | H4: Patience Agent | I4: Resilience | J4: Resilience Agent | K4: Dept Total /4 | L4: Coordination /1 | M4: Quadrant
A5: 1 · Strategy Hub | B5: STR-00 | D5: STR-02 | F5: STR-03 | H5: STR-01 | J5: STR-05 | K5: =SUM(C5,E5,G5,I5) -> 0 | M5: High Yin
A6: 2 · Marketing Hub | B6: MKT-00 | D6: MKT-03 | F6: MKT-02 | H6: MKT-00 | J6: MKT-01 | K6: =SUM(C6,E6,G6,I6) -> 0 | M6: High Yang
A7: 3 · Sales Hub | B7: SAL-00 | D7: SAL-09 | F7: SAL-07 | H7: SAL-12 | J7: SAL-03 | K7: =SUM(C7,E7,G7,I7) -> 0 | M7: High Yang
A8: 4 · Operations Hub | B8: OPS-00 | D8: OPS-02 | F8: OPS-03 | H8: OPS-03 | J8: OPS-04 | K8: =SUM(C8,E8,G8,I8) -> 0 | M8: High Yang
A9: 5 · Finance Hub | B9: FIN-00 | D9: FIN-04 | F9: FIN-03 | H9: FIN-02 | J9: FIN-01 | K9: =SUM(C9,E9,G9,I9) -> 0 | M9: High Yin
A10: 6 · HR & Culture Hub | B10: HRC-00 | D10: HRC-04 | F10: HRC-06 | H10: HRC-01 | J10: HRC-10 | K10: =SUM(C10,E10,G10,I10) -> 0 | M10: High Yin
A11: 7 · Technology Hub | B11: TEC-00 | D11: OPS-02 | F11: TEC-04 | H11: TEC-01 | J11: TEC-08 | K11: =SUM(C11,E11,G11,I11) -> 0 | M11: Bridging
A12: 8 · Client Success Hub | B12: CS-00 | D12: CS-03 | F12: CS-04 | H12: CS-10 | J12: CS-08 | K12: =SUM(C12,E12,G12,I12) -> 0 | M12: Bridging
A13: 9 · Content Hub | B13: CON-00 | D13: CON-03 | F13: CON-01 | H13: CON-05 | J13: CON-08 | K13: =SUM(C13,E13,G13,I13) -> 0 | M13: High Yin
A14: TOTALS | C14: =SUM(C5:C13) -> 0 | E14: =SUM(E5:E13) -> 0 | G14: =SUM(G5:G13) -> 0 | I14: =SUM(I5:I13) -> 0 | K14: =SUM(K5:K13) -> 0 | L14: =SUM(L5:L13) -> 0
A16: EXAMPLE (not counted) | B16: SAL-00 | C16: 1 | E16: 0.5 | G16: 0.5 | I16: 0 | K16: =SUM(C16,E16,G16,I16) -> 2 | L16: 0.5 | M16: High Yang
A18: BEAS Total /45 | B18: =K14+L14 -> 0
A19: Band | B19: =IF(COUNT(C5:C13,E5:E13,G5:G13,I5:I13)=0,"Not yet scored",IF(B18>=40,"Dynamic Middle—Sustained",IF(B18>=32,"Equilibrium—Functional",IF(B18>=24,"Imbalance—Managed",IF(B18>=16,"Imbalance—Exposed","Collapse Risk"))))) -> Not yet scored
A20: Canon action | B20: =IF(B19="Not yet scored","—",IF(B18>=40,"Scale intentionally. Begin next Fibonacci step. (O-04 → STR-03)",IF(B18>=32,"Identify lowest-scoring department. Apply Shepherd's Way. (O-04 → O-03)",IF(B18>=24,"Gap analysis. Prioritize by dependency order. (O-04 → O-03)",IF(B18>=16,"Return to Gather. Full Immersion Model recommended. (O-03)","Emergency blueprint session. Minimum viable docs in 9 depts within 30 days. (O-19 + G-00)"))))) -> —
A21: Lowest department total | B21: =IF(B19="Not yet scored","—",INDEX(A5:A13,MATCH(MIN(K5:K13),K5:K13,0))) -> —
A22: High Yang quadrant avg /4 | B22: =AVERAGE(K6:K8) -> 0
A23: High Yin quadrant avg /4 | B23: =AVERAGE(K5,K9,K10,K13) -> 0
A24: Bridging quadrant avg /4 | B24: =AVERAGE(K11:K12) -> 0
A26: Pillar evidence (what 'fully implemented' looks like) — v5.1 L1362–1367
A27: Correctness | B27: Every move objectively sound; no shortcuts (97% accuracy → 16% perfection over 60 decisions). In practice: documented SOPs, tested automations before launch, blueprint review before any build, every Komodo recording. (Pillar steward: OPS-02)
A28: Complexity | B28: Embrace full scope; never oversimplify. In practice: nine integrated departments, no isolated tools, Gather step before any build. (Pillar steward: TEC-04)
A29: Patience | B29: Growth through position, not desperation; blueprint first. In practice: 5-phase implementation, Direct → Guide → Gather before any system is built, quarterly BEAS assessment. (Pillar steward: O-03)
A30: Resilience | B30: Survive pressure without collapse; productive entropy. In practice: Komodo-recorded processes, full documentation, never fully dependent on any single third party, downgrade path to $297. (Pillar steward: STR-05)

Sheet Workflows
A1: Workflow ID | B1: Workflow | C1: Seq | D1: Agent ID | E1: Agent Name | F1: Action | G1: Hands Off To
A2: W01 | B2: Lead-to-Cash (ACE Acquisition → Creation) | C2: 1 | D2: O-01 | E2: =IFERROR(INDEX('Agent Roster'!$B:$B,MATCH(D2,'Agent Roster'!$A:$A,0)),"(group / any)") -> Intake & Triage Agent (Layer 0 Base Code) | F2: Input arrives (ad, form, referral) | G2: MKT-03
A3: W01 | B3: Lead-to-Cash (ACE Acquisition → Creation) | C3: 2 | D3: MKT-03 | E3: =IFERROR(INDEX('Agent Roster'!$B:$B,MATCH(D3,'Agent Roster'!$A:$A,0)),"(group / any)") -> Lead Capture, Tagging & Channel ROI Agent | F3: Capture in Lead Connector; tag source/campaign/hot buttons | G3: SAL-01
A4: W01 | B4: Lead-to-Cash (ACE Acquisition → Creation) | C4: 3 | D4: SAL-01 | E4: =IFERROR(INDEX('Agent Roster'!$B:$B,MATCH(D4,'Agent Roster'!$A:$A,0)),"(group / any)") -> Instant Response Agent | F4: Instant automated first contact (Flows AI) → Contacted | G4: SAL-02
A5: W01 | B5: Lead-to-Cash (ACE Acquisition → Creation) | C5: 4 | D5: SAL-02 | E5: =IFERROR(INDEX('Agent Roster'!$B:$B,MATCH(D5,'Agent Roster'!$A:$A,0)),"(group / any)") -> Lead Qualification Agent | F5: Short-survey qualification → Qualified | G5: SAL-04
A6: W01 | B6: Lead-to-Cash (ACE Acquisition → Creation) | C6: 5 | D6: SAL-04 | E6: =IFERROR(INDEX('Agent Roster'!$B:$B,MATCH(D6,'Agent Roster'!$A:$A,0)),"(group / any)") -> Appointment & Show-Rate Agent | F6: Book and confirm call → Appointment Set / Show | G6: SAL-05
A7: W01 | B7: Lead-to-Cash (ACE Acquisition → Creation) | C7: 6 | D7: SAL-05 | E7: =IFERROR(INDEX('Agent Roster'!$B:$B,MATCH(D7,'Agent Roster'!$A:$A,0)),"(group / any)") -> Sales Call Copilot (7-Step Script) | F7: Pre-call brief; human closer runs 7-step script | G7: SAL-06
A8: W01 | B8: Lead-to-Cash (ACE Acquisition → Creation) | C8: 7 | D8: SAL-06 | E8: =IFERROR(INDEX('Agent Roster'!$B:$B,MATCH(D8,'Agent Roster'!$A:$A,0)),"(group / any)") -> Objection Handling Coach (I.A.C.E.) | F8: I.A.C.E. on objections | G8: SAL-07
A9: W01 | B9: Lead-to-Cash (ACE Acquisition → Creation) | C9: 8 | D9: SAL-07 | E9: =IFERROR(INDEX('Agent Roster'!$B:$B,MATCH(D9,'Agent Roster'!$A:$A,0)),"(group / any)") -> Offer Architect | F9: Present three-tier stack; prospect self-selects | G9: SAL-08
A10: W01 | B10: Lead-to-Cash (ACE Acquisition → Creation) | C10: 9 | D10: SAL-08 | E10: =IFERROR(INDEX('Agent Roster'!$B:$B,MATCH(D10,'Agent Roster'!$A:$A,0)),"(group / any)") -> Proposal & Contract Generator | F10: Draft proposal/contract from notes → Proposal | G10: G-00
A11: W01 | B11: Lead-to-Cash (ACE Acquisition → Creation) | C11: 10 | D11: G-00 | E11: =IFERROR(INDEX('Agent Roster'!$B:$B,MATCH(D11,'Agent Roster'!$A:$A,0)),"(group / any)") -> Founder / Operator (HUMAN) | F11: Human approves and signs | G11: SAL-11
A12: W01 | B12: Lead-to-Cash (ACE Acquisition → Creation) | C12: 11 | D12: SAL-11 | E12: =IFERROR(INDEX('Agent Roster'!$B:$B,MATCH(D12,'Agent Roster'!$A:$A,0)),"(group / any)") -> Sales-to-Onboarding Handoff Agent | F12: Closed Won → handoff package with full context | G12: FIN-07
A13: W01 | B13: Lead-to-Cash (ACE Acquisition → Creation) | C13: 12 | D13: FIN-07 | E13: =IFERROR(INDEX('Agent Roster'!$B:$B,MATCH(D13,'Agent Roster'!$A:$A,0)),"(group / any)") -> Capital Flow Accounting & Collections Agent | F13: Invoice and record payment | G13: FIN-05
... A109: W15 | B109: Agent fleet change | C109: 6 | D109: G-04 | E109: =IFERROR(INDEX('Agent Roster'!$B:$B,MATCH(D109,'Agent Roster'!$A:$A,0)),"(group / any)") -> Framework Compliance Auditor | F109: Audit first runs | G109: — (cycle closes)

Sheet Human Gates
A1: Gate ID | B1: Decision Agents Must Escalate | C1: Raised By | D1: Basis | E1: Canon Location | F1: Decides
A2: HG-01 | B2: Any material decision (the choice itself) | C2: O-16 | D2: Framework cannot supply the choice | E2: v5.1 L172 | F2: G-00
A3: HG-02 | B3: Naming the outcome after an action (e.g., 'success', 'failure') | C3: Any | D3: Framework cannot supply the naming | E3: v5.1 L174 | F3: G-00
A4: HG-03 | B4: Situation-specific measurements an agent cannot take | C4: G-03 | D4: Framework cannot supply empirical measurements | E4: v5.1 L176 | F4: G-00
A5: HG-04 | B5: Stance on a held-open variable / any stipulation | C5: G-01 | D5: Stipulations are operator choices (v5.3) | E5: v5.3 §2 | F5: G-00
A6: HG-05 | B6: Strategic Direct (intent) for hub-level builds | C6: O-03 | D6: Direct begins from Third-Kingdom awareness | E6: v5.1 L1488–1497 | F6: G-00
A7: HG-06 | B7: Sales conversation (Creation stage) | C7: SAL-05 | D7: 'The human magic happens here' | E7: v5.1 L1603 | F7: G-00
A8: HG-07 | B8: Honest escalation / walk-away on an objection or negotiation | C8: SAL-06; SAL-10 | D8: Eliminate or Escalate — the honest path | E8: v5.1 L1637; L2589 | F8: G-00
A9: HG-08 | B9: Contract signature; final negotiated terms | C9: SAL-08; SAL-10 | D9: Derived (commitment) | E9: Derived | F9: G-00
A10: HG-09 | B10: Price and offer changes | C10: FIN-06; SAL-07 | D10: Derived (commercial authority) | E10: Derived | F10: G-00
A11: HG-10 | B11: Capital deployment; budget approval | C11: FIN-01; FIN-02 | D11: Derived (capital authority) | E11: Derived | F11: G-00
A12: HG-11 | B12: Hire, compensation, employment decisions | C12: HRC-01; HRC-02; HRC-04 | D12: Derived (employment law/ethics) | E12: Derived | F12: G-00
... A22: HG-21 | B22: Psychological, health, family, grief, spiritual matters | C22: G-00 | D22: Human-reserved algorithms — not delegated to agents | E22: Derived (care boundary) | F22: G-00

Sheet Held-Open Variables
A1: Var ID | B1: Variable | C1: Why Open (canon status) | D1: How It Narrows / Who | E1: Status
A2: V-01 | B2: KPI thresholds (response times beyond 'instant', conversion targets, NPS target, DSO, churn %) | C2: Canon names the metrics, not the numbers | D2: Operator sets from own baseline measurements | E2: Held open
A3: V-02 | B3: BEAS band calibration across industries / growth stages | C3: v5.2 Run 4: 'exact band calibration across the 52 industries/stages (bounded)' | D3: Track BEAS vs outcomes over cycles | E3: Held open (bounded)
A4: V-03 | B4: Is the 9-department × 4-pillar decomposition substrate-dependent? | C4: v5.2 Run 4 opened this variable | D4: Test whether these nine hubs fit this specific business | E4: Held open
A5: V-04 | B5: Does the co-creator proof hold for an AI or a collective? | C5: v5.2 Run 5: held open — directly relevant to agents | D5: Do not treat agents as co-creators; choice stays human (G-00) | E5: Held open
A6: V-05 | B6: Autonomy level of each agent (A / H / L / R) | C6: Derived in this map; canon does not assign autonomy | D6: Operator adjusts per risk appetite; G-06 records | E6: Stipulation
A7: V-06 | B7: Agent placement where canon names no hub (Risk, Innovation, Vendor, Compliance, Negotiation, Writing, Facilitation, Learning, Memory, Communication) | C7: Derived placement | D7: Re-home freely; responsibilities do not change | E7: Stipulation
A8: V-07 | B8: Growth stage of the business (pre-revenue / scaling / mature) | C8: Canon gives tilts per stage, not the classification | D8: Founder classifies monthly (HG-16) | E8: Held open
A9: V-08 | B9: Tool stack beyond those canon names (Lead Connector/GHL, Flows AI, n8n, Komodo, GFunnel University) | C9: Not supplied | D9: Operator selects; record in TEC-01 architecture doc | E9: Held open
A10: V-09 | B10: Compensation numbers, prices other than the $297 downgrade path, budgets | C10: Not supplied | D10: Measured / decided by humans | E10: Held open
A11: V-10 | B11: Legal jurisdiction and regulatory framework | C11: Not supplied | D11: HRC-10 maps once jurisdiction is known | E11: Held open
A12: V-11 | B12: Number of agent instances per role (e.g., several SAL-01 instances) | C12: Not supplied | D12: Size from volume measurements | E12: Held open
... A15: V-14 | B15: v5.4 constructs (Line-Field, Knot-Line, Lamina) in business operations | C15: v5.4 states zero novel predictions; not physics; not business ops | D15: Excluded from this map | E15: Excluded

Sheet Gap Check
A1: Gap Check — live proof of 'no gaps'
A2: Check | B2: Value | C2: Rule
A3: Agents in roster | B3: =COUNTA('Agent Roster'!A2:A113) -> 112 | C3: —
A4: Agents with zero responsibilities | B4: =COUNTIF('Agent Roster'!T2:T113,0) -> 0 | C4: must be 0
A5: Responsibilities | B5: =COUNTA(Responsibilities!A2:A957) -> 956 | C5: —
A6: Responsibilities with no valid owner | B6: =COUNTIF(Responsibilities!C2:C957,"UNASSIGNED") -> 0 | C6: must be 0
A7: Algorithms in canon (parsed) | B7: =COUNTA('Algorithm Coverage'!A2:A78) -> 77 | C7: 77 expected
A8: Algorithm steps in canon | B8: =SUM('Algorithm Coverage'!C2:C78) -> 662 | C8: —
A9: Algorithm steps unmapped | B9: =SUM('Algorithm Coverage'!E2:E78) -> 0 | C9: must be 0
A10: Canon table elements uncovered | B10: =COUNTIF('Canon Element Coverage'!G2:G183,"GAP") -> 0 | C10: must be 0
A11: Workflow steps with unknown agent | B11: =COUNTIF(Workflows!E2:E109,"(group / any)") -> 3 | C11: group steps (Hub leads / Any agent) are intentional
A12: OVERALL | B12: =IF(AND(B4=0,B6=0,B9=0,B10=0),"NO GAPS — every responsibility owned, every agent active, every canon step mapped","GAPS FOUND — see red cells") -> NO GAPS — every responsibility owned, every agent active, every canon step mapped
A14: Agents by tier
A15: Tier 0 | B15: =COUNTIF('Agent Roster'!C2:C113,"0*") -> 8
A16: Tier 1 | B16: =COUNTIF('Agent Roster'!C2:C113,"1*") -> 22
A17: Tier 2 | B17: =COUNTIF('Agent Roster'!C2:C113,"2*") -> 9
A18: Tier 3 | B18: =COUNTIF('Agent Roster'!C2:C113,"3*") -> 73
A20: Agents by autonomy
A21: Autonomous — agent executes and logs | B21: =COUNTIF('Agent Roster'!Q2:Q113,"A") -> 49
A22: Human-in-loop — agent drafts, human approves | B22: =COUNTIF('Agent Roster'!Q2:Q113,"H") -> 52
A23: Human-led — agent assists | B23: =COUNTIF('Agent Roster'!Q2:Q113,"L") -> 10
A24: Human-reserved — no agent executes | B24: =COUNTIF('Agent Roster'!Q2:Q113,"R") -> 1
A26: Responsibilities per hub
A27: Governance & Meta-Tier | B27: =COUNTIF(Responsibilities!D2:D957,A27) -> 188
A28: Orchestration & Diagnostics | B28: =COUNTIF(Responsibilities!D2:D957,A28) -> 276
A29: 1 · Strategy Hub | B29: =COUNTIF(Responsibilities!D2:D957,A29) -> 55
A30: 2 · Marketing Hub | B30: =COUNTIF(Responsibilities!D2:D957,A30) -> 37
A31: 3 · Sales Hub | B31: =COUNTIF(Responsibilities!D2:D957,A31) -> 80
A32: 4 · Operations Hub | B32: =COUNTIF(Responsibilities!D2:D957,A32) -> 32
A33: 5 · Finance Hub | B33: =COUNTIF(Responsibilities!D2:D957,A33) -> 34
A34: 6 · HR & Culture Hub | B34: =COUNTIF(Responsibilities!D2:D957,A34) -> 81
A35: 7 · Technology Hub | B35: =COUNTIF(Responsibilities!D2:D957,A35) -> 39
A36: 8 · Client Success Hub | B36: =COUNTIF(Responsibilities!D2:D957,A36) -> 61
A37: 9 · Content Hub | B37: =COUNTIF(Responsibilities!D2:D957,A37) -> 73
